<?xml version="1.0" encoding="ISO-8859-1" ?> 
<ans:mensagemTISS xmlns:ans="http://www.ans.gov.br/padroes/tiss/schemas" xmlns:xsi="http://www.w3.org/2001/XMLSchema-instance" xsi:schemaLocation="http://www.ans.gov.br/padroes/tiss/schemas http://www.ans.gov.br/padroes/tiss/schemas/tissV4_01_00.xsd">
<ans:cabecalho>
<ans:identificacaoTransacao>
<ans:tipoTransacao>ENVIO_LOTE_GUIAS</ans:tipoTransacao>
<ans:sequencialTransacao>304678</ans:sequencialTransacao>
<ans:dataRegistroTransacao>2025-10-20</ans:dataRegistroTransacao>
<ans:horaRegistroTransacao>14:20:57</ans:horaRegistroTransacao>
</ans:identificacaoTransacao>
<ans:origem>
<ans:identificacaoPrestador>
<ans:codigoPrestadorNaOperadora>110020</ans:codigoPrestadorNaOperadora>
</ans:identificacaoPrestador>
</ans:origem>
<ans:destino>
<ans:registroANS>335100</ans:registroANS>
</ans:destino>
<ans:Padrao>4.01.00</ans:Padrao>
</ans:cabecalho>
<ans:prestadorParaOperadora>
<ans:loteGuias>
<ans:numeroLote>6094</ans:numeroLote>
<ans:guiasTISS>
<ans:guiaSP-SADT>
<ans:cabecalhoGuia>
<ans:registroANS>335100</ans:registroANS>
<ans:numeroGuiaPrestador>242067</ans:numeroGuiaPrestador>
<ans:guiaPrincipal>22-54280638</ans:guiaPrincipal>
</ans:cabecalhoGuia>
<ans:dadosAutorizacao>
<ans:numeroGuiaOperadora>22-54280638</ans:numeroGuiaOperadora>
<ans:dataAutorizacao>2025-10-11</ans:dataAutorizacao>
<ans:senha>22-54280638</ans:senha>
</ans:dadosAutorizacao>
<ans:dadosBeneficiario>
<ans:numeroCarteira>00300499001929106</ans:numeroCarteira>
<ans:atendimentoRN>N</ans:atendimentoRN>
</ans:dadosBeneficiario>
<ans:dadosSolicitante>
<ans:contratadoSolicitante>
<ans:codigoPrestadorNaOperadora>110020</ans:codigoPrestadorNaOperadora>
</ans:contratadoSolicitante>
<ans:nomeContratadoSolicitante>Centro Medico Rio Preto S.a</ans:nomeContratadoSolicitante>
<ans:profissionalSolicitante>
<ans:nomeProfissional>Andrey Jose Mamed Jordao</ans:nomeProfissional>
<ans:conselhoProfissional>06</ans:conselhoProfissional>
<ans:numeroConselhoProfissional>271637</ans:numeroConselhoProfissional>
<ans:UF>35</ans:UF>
<ans:CBOS>225260</ans:CBOS>
</ans:profissionalSolicitante>
</ans:dadosSolicitante>
<ans:dadosSolicitacao>
<ans:dataSolicitacao>2025-10-11</ans:dataSolicitacao>
<ans:caraterAtendimento>2</ans:caraterAtendimento>
<ans:indicacaoClinica>NAUSEA E VOMITOS</ans:indicacaoClinica>
</ans:dadosSolicitacao>
<ans:dadosExecutante>
<ans:contratadoExecutante>
<ans:codigoPrestadorNaOperadora>110020</ans:codigoPrestadorNaOperadora>
</ans:contratadoExecutante>
<ans:CNES>2097117</ans:CNES>
</ans:dadosExecutante>
<ans:dadosAtendimento>
<ans:tipoAtendimento>04</ans:tipoAtendimento>
<ans:indicacaoAcidente>9</ans:indicacaoAcidente>
<ans:tipoConsulta>1</ans:tipoConsulta>
<ans:regimeAtendimento>04</ans:regimeAtendimento>
</ans:dadosAtendimento>
<ans:procedimentosExecutados>
<ans:procedimentoExecutado>
<ans:sequencialItem>1</ans:sequencialItem>
<ans:dataExecucao>2025-10-11</ans:dataExecucao>
<ans:horaInicial>19:02:14</ans:horaInicial>
<ans:horaFinal>19:02:14</ans:horaFinal>
<ans:procedimento>
<ans:codigoTabela>98</ans:codigoTabela>
<ans:codigoProcedimento>98200709</ans:codigoProcedimento>
<ans:descricaoProcedimento>Consulta De Urgencia Global</ans:descricaoProcedimento>
</ans:procedimento>
<ans:quantidadeExecutada>1</ans:quantidadeExecutada>
<ans:viaAcesso>1</ans:viaAcesso>
<ans:tecnicaUtilizada>1</ans:tecnicaUtilizada>
<ans:reducaoAcrescimo>1.00</ans:reducaoAcrescimo>
<ans:valorUnitario>69.00</ans:valorUnitario>
<ans:valorTotal>69.00</ans:valorTotal>
<ans:equipeSadt>
<ans:grauPart>12</ans:grauPart>
<ans:codProfissional>
<ans:codigoPrestadorNaOperadora>110020</ans:codigoPrestadorNaOperadora>
</ans:codProfissional>
<ans:nomeProf>Ronaldo Gonçalves Da Silva</ans:nomeProf>
<ans:conselho>06</ans:conselho>
<ans:numeroConselhoProfissional>139120</ans:numeroConselhoProfissional>
<ans:UF>35</ans:UF>
<ans:CBOS>225125</ans:CBOS>
</ans:equipeSadt>
</ans:procedimentoExecutado>
<ans:procedimentoExecutado>
<ans:sequencialItem>2</ans:sequencialItem>
<ans:dataExecucao>2025-10-11</ans:dataExecucao>
<ans:horaInicial>19:33:10</ans:horaInicial>
<ans:horaFinal>19:33:10</ans:horaFinal>
<ans:procedimento>
<ans:codigoTabela>22</ans:codigoTabela>
<ans:codigoProcedimento>10101039</ans:codigoProcedimento>
<ans:descricaoProcedimento>Consulta Em Pronto Socorro</ans:descricaoProcedimento>
</ans:procedimento>
<ans:quantidadeExecutada>1</ans:quantidadeExecutada>
<ans:viaAcesso>1</ans:viaAcesso>
<ans:tecnicaUtilizada>1</ans:tecnicaUtilizada>
<ans:reducaoAcrescimo>1.00</ans:reducaoAcrescimo>
<ans:valorUnitario>115.42</ans:valorUnitario>
<ans:valorTotal>115.42</ans:valorTotal>
<ans:equipeSadt>
<ans:grauPart>12</ans:grauPart>
<ans:codProfissional>
<ans:cpfContratado>00000271637</ans:cpfContratado>
</ans:codProfissional>
<ans:nomeProf>Andrey Jose Mamed Jordao</ans:nomeProf>
<ans:conselho>06</ans:conselho>
<ans:numeroConselhoProfissional>271637</ans:numeroConselhoProfissional>
<ans:UF>35</ans:UF>
<ans:CBOS>225260</ans:CBOS>
</ans:equipeSadt>
</ans:procedimentoExecutado>
</ans:procedimentosExecutados>
<ans:valorTotal>
<ans:valorProcedimentos>184.42</ans:valorProcedimentos>
<ans:valorTotalGeral>184.42</ans:valorTotalGeral>
</ans:valorTotal>
</ans:guiaSP-SADT>
<ans:guiaSP-SADT>
<ans:cabecalhoGuia>
<ans:registroANS>335100</ans:registroANS>
<ans:numeroGuiaPrestador>245078</ans:numeroGuiaPrestador>
<ans:guiaPrincipal>23-54372611</ans:guiaPrincipal>
</ans:cabecalhoGuia>
<ans:dadosAutorizacao>
<ans:numeroGuiaOperadora>23-54372611</ans:numeroGuiaOperadora>
<ans:dataAutorizacao>2025-10-16</ans:dataAutorizacao>
<ans:senha>23-54372611</ans:senha>
</ans:dadosAutorizacao>
<ans:dadosBeneficiario>
<ans:numeroCarteira>09700033000808799</ans:numeroCarteira>
<ans:atendimentoRN>N</ans:atendimentoRN>
</ans:dadosBeneficiario>
<ans:dadosSolicitante>
<ans:contratadoSolicitante>
<ans:codigoPrestadorNaOperadora>110020</ans:codigoPrestadorNaOperadora>
</ans:contratadoSolicitante>
<ans:nomeContratadoSolicitante>Centro Medico Rio Preto S.a</ans:nomeContratadoSolicitante>
<ans:profissionalSolicitante>
<ans:nomeProfissional>Matheus Alberto Fogolin Elias</ans:nomeProfissional>
<ans:conselhoProfissional>06</ans:conselhoProfissional>
<ans:numeroConselhoProfissional>263739</ans:numeroConselhoProfissional>
<ans:UF>35</ans:UF>
<ans:CBOS>225125</ans:CBOS>
</ans:profissionalSolicitante>
</ans:dadosSolicitante>
<ans:dadosSolicitacao>
<ans:dataSolicitacao>2025-10-16</ans:dataSolicitacao>
<ans:caraterAtendimento>2</ans:caraterAtendimento>
<ans:indicacaoClinica>DIARREIA E GASTROENTERITE DE ORIGEM INFECCIOSA PRESUMIVEL</ans:indicacaoClinica>
</ans:dadosSolicitacao>
<ans:dadosExecutante>
<ans:contratadoExecutante>
<ans:codigoPrestadorNaOperadora>110020</ans:codigoPrestadorNaOperadora>
</ans:contratadoExecutante>
<ans:CNES>2097117</ans:CNES>
</ans:dadosExecutante>
<ans:dadosAtendimento>
<ans:tipoAtendimento>04</ans:tipoAtendimento>
<ans:indicacaoAcidente>9</ans:indicacaoAcidente>
<ans:tipoConsulta>1</ans:tipoConsulta>
<ans:regimeAtendimento>04</ans:regimeAtendimento>
</ans:dadosAtendimento>
<ans:procedimentosExecutados>
<ans:procedimentoExecutado>
<ans:sequencialItem>1</ans:sequencialItem>
<ans:dataExecucao>2025-10-16</ans:dataExecucao>
<ans:horaInicial>10:25:34</ans:horaInicial>
<ans:horaFinal>10:25:34</ans:horaFinal>
<ans:procedimento>
<ans:codigoTabela>98</ans:codigoTabela>
<ans:codigoProcedimento>98200709</ans:codigoProcedimento>
<ans:descricaoProcedimento>Consulta De Urgencia Global</ans:descricaoProcedimento>
</ans:procedimento>
<ans:quantidadeExecutada>1</ans:quantidadeExecutada>
<ans:viaAcesso>1</ans:viaAcesso>
<ans:tecnicaUtilizada>1</ans:tecnicaUtilizada>
<ans:reducaoAcrescimo>1.00</ans:reducaoAcrescimo>
<ans:valorUnitario>99.08</ans:valorUnitario>
<ans:valorTotal>99.08</ans:valorTotal>
<ans:equipeSadt>
<ans:grauPart>12</ans:grauPart>
<ans:codProfissional>
<ans:codigoPrestadorNaOperadora>110020</ans:codigoPrestadorNaOperadora>
</ans:codProfissional>
<ans:nomeProf>Ronaldo Gonçalves Da Silva</ans:nomeProf>
<ans:conselho>06</ans:conselho>
<ans:numeroConselhoProfissional>139120</ans:numeroConselhoProfissional>
<ans:UF>35</ans:UF>
<ans:CBOS>225125</ans:CBOS>
</ans:equipeSadt>
</ans:procedimentoExecutado>
<ans:procedimentoExecutado>
<ans:sequencialItem>2</ans:sequencialItem>
<ans:dataExecucao>2025-10-16</ans:dataExecucao>
<ans:horaInicial>10:44:29</ans:horaInicial>
<ans:horaFinal>10:44:29</ans:horaFinal>
<ans:procedimento>
<ans:codigoTabela>22</ans:codigoTabela>
<ans:codigoProcedimento>10101039</ans:codigoProcedimento>
<ans:descricaoProcedimento>Consulta Em Pronto Socorro</ans:descricaoProcedimento>
</ans:procedimento>
<ans:quantidadeExecutada>1</ans:quantidadeExecutada>
<ans:viaAcesso>1</ans:viaAcesso>
<ans:tecnicaUtilizada>1</ans:tecnicaUtilizada>
<ans:reducaoAcrescimo>1.00</ans:reducaoAcrescimo>
<ans:valorUnitario>85.35</ans:valorUnitario>
<ans:valorTotal>85.35</ans:valorTotal>
<ans:equipeSadt>
<ans:grauPart>12</ans:grauPart>
<ans:codProfissional>
<ans:cpfContratado>00000263739</ans:cpfContratado>
</ans:codProfissional>
<ans:nomeProf>Matheus Alberto Fogolin Elias</ans:nomeProf>
<ans:conselho>06</ans:conselho>
<ans:numeroConselhoProfissional>263739</ans:numeroConselhoProfissional>
<ans:UF>35</ans:UF>
<ans:CBOS>225125</ans:CBOS>
</ans:equipeSadt>
</ans:procedimentoExecutado>
</ans:procedimentosExecutados>
<ans:valorTotal>
<ans:valorProcedimentos>184.43</ans:valorProcedimentos>
<ans:valorTotalGeral>184.43</ans:valorTotalGeral>
</ans:valorTotal>
</ans:guiaSP-SADT>
<ans:guiaSP-SADT>
<ans:cabecalhoGuia>
<ans:registroANS>335100</ans:registroANS>
<ans:numeroGuiaPrestador>234201</ans:numeroGuiaPrestador>
<ans:guiaPrincipal>22-54040418</ans:guiaPrincipal>
</ans:cabecalhoGuia>
<ans:dadosAutorizacao>
<ans:numeroGuiaOperadora>22-54040418</ans:numeroGuiaOperadora>
<ans:dataAutorizacao>2025-09-30</ans:dataAutorizacao>
<ans:senha>22-54040418</ans:senha>
</ans:dadosAutorizacao>
<ans:dadosBeneficiario>
<ans:numeroCarteira>00308083000001012</ans:numeroCarteira>
<ans:atendimentoRN>N</ans:atendimentoRN>
</ans:dadosBeneficiario>
<ans:dadosSolicitante>
<ans:contratadoSolicitante>
<ans:codigoPrestadorNaOperadora>110020</ans:codigoPrestadorNaOperadora>
</ans:contratadoSolicitante>
<ans:nomeContratadoSolicitante>Centro Medico Rio Preto S.a</ans:nomeContratadoSolicitante>
<ans:profissionalSolicitante>
<ans:nomeProfissional>Matheus Alberto Fogolin Elias</ans:nomeProfissional>
<ans:conselhoProfissional>06</ans:conselhoProfissional>
<ans:numeroConselhoProfissional>263739</ans:numeroConselhoProfissional>
<ans:UF>35</ans:UF>
<ans:CBOS>225125</ans:CBOS>
</ans:profissionalSolicitante>
</ans:dadosSolicitante>
<ans:dadosSolicitacao>
<ans:dataSolicitacao>2025-09-30</ans:dataSolicitacao>
<ans:caraterAtendimento>2</ans:caraterAtendimento>
<ans:indicacaoClinica>CEFALEIA</ans:indicacaoClinica>
</ans:dadosSolicitacao>
<ans:dadosExecutante>
<ans:contratadoExecutante>
<ans:codigoPrestadorNaOperadora>110020</ans:codigoPrestadorNaOperadora>
</ans:contratadoExecutante>
<ans:CNES>2097117</ans:CNES>
</ans:dadosExecutante>
<ans:dadosAtendimento>
<ans:tipoAtendimento>04</ans:tipoAtendimento>
<ans:indicacaoAcidente>9</ans:indicacaoAcidente>
<ans:tipoConsulta>1</ans:tipoConsulta>
<ans:regimeAtendimento>04</ans:regimeAtendimento>
</ans:dadosAtendimento>
<ans:procedimentosExecutados>
<ans:procedimentoExecutado>
<ans:sequencialItem>1</ans:sequencialItem>
<ans:dataExecucao>2025-09-30</ans:dataExecucao>
<ans:horaInicial>11:01:49</ans:horaInicial>
<ans:horaFinal>11:01:49</ans:horaFinal>
<ans:procedimento>
<ans:codigoTabela>98</ans:codigoTabela>
<ans:codigoProcedimento>98200709</ans:codigoProcedimento>
<ans:descricaoProcedimento>Consulta De Urgencia Global</ans:descricaoProcedimento>
</ans:procedimento>
<ans:quantidadeExecutada>1</ans:quantidadeExecutada>
<ans:viaAcesso>1</ans:viaAcesso>
<ans:tecnicaUtilizada>1</ans:tecnicaUtilizada>
<ans:reducaoAcrescimo>1.00</ans:reducaoAcrescimo>
<ans:valorUnitario>69.00</ans:valorUnitario>
<ans:valorTotal>69.00</ans:valorTotal>
<ans:equipeSadt>
<ans:grauPart>12</ans:grauPart>
<ans:codProfissional>
<ans:codigoPrestadorNaOperadora>110020</ans:codigoPrestadorNaOperadora>
</ans:codProfissional>
<ans:nomeProf>Ronaldo Gonçalves Da Silva</ans:nomeProf>
<ans:conselho>06</ans:conselho>
<ans:numeroConselhoProfissional>139120</ans:numeroConselhoProfissional>
<ans:UF>35</ans:UF>
<ans:CBOS>225125</ans:CBOS>
</ans:equipeSadt>
</ans:procedimentoExecutado>
<ans:procedimentoExecutado>
<ans:sequencialItem>2</ans:sequencialItem>
<ans:dataExecucao>2025-09-30</ans:dataExecucao>
<ans:horaInicial>11:22:19</ans:horaInicial>
<ans:horaFinal>11:22:19</ans:horaFinal>
<ans:procedimento>
<ans:codigoTabela>22</ans:codigoTabela>
<ans:codigoProcedimento>10101039</ans:codigoProcedimento>
<ans:descricaoProcedimento>Consulta Em Pronto Socorro</ans:descricaoProcedimento>
</ans:procedimento>
<ans:quantidadeExecutada>1</ans:quantidadeExecutada>
<ans:viaAcesso>1</ans:viaAcesso>
<ans:tecnicaUtilizada>1</ans:tecnicaUtilizada>
<ans:reducaoAcrescimo>1.00</ans:reducaoAcrescimo>
<ans:valorUnitario>115.42</ans:valorUnitario>
<ans:valorTotal>115.42</ans:valorTotal>
<ans:equipeSadt>
<ans:grauPart>12</ans:grauPart>
<ans:codProfissional>
<ans:cpfContratado>00000263739</ans:cpfContratado>
</ans:codProfissional>
<ans:nomeProf>Matheus Alberto Fogolin Elias</ans:nomeProf>
<ans:conselho>06</ans:conselho>
<ans:numeroConselhoProfissional>263739</ans:numeroConselhoProfissional>
<ans:UF>35</ans:UF>
<ans:CBOS>225125</ans:CBOS>
</ans:equipeSadt>
</ans:procedimentoExecutado>
</ans:procedimentosExecutados>
<ans:valorTotal>
<ans:valorProcedimentos>184.42</ans:valorProcedimentos>
<ans:valorTotalGeral>184.42</ans:valorTotalGeral>
</ans:valorTotal>
</ans:guiaSP-SADT>
<ans:guiaSP-SADT>
<ans:cabecalhoGuia>
<ans:registroANS>335100</ans:registroANS>
<ans:numeroGuiaPrestador>234189</ans:numeroGuiaPrestador>
<ans:guiaPrincipal>22-54039973</ans:guiaPrincipal>
</ans:cabecalhoGuia>
<ans:dadosAutorizacao>
<ans:numeroGuiaOperadora>22-54039973</ans:numeroGuiaOperadora>
<ans:dataAutorizacao>2025-09-30</ans:dataAutorizacao>
<ans:senha>22-54039973</ans:senha>
</ans:dadosAutorizacao>
<ans:dadosBeneficiario>
<ans:numeroCarteira>00303590200001013</ans:numeroCarteira>
<ans:atendimentoRN>N</ans:atendimentoRN>
</ans:dadosBeneficiario>
<ans:dadosSolicitante>
<ans:contratadoSolicitante>
<ans:codigoPrestadorNaOperadora>110020</ans:codigoPrestadorNaOperadora>
</ans:contratadoSolicitante>
<ans:nomeContratadoSolicitante>Centro Medico Rio Preto S.a</ans:nomeContratadoSolicitante>
<ans:profissionalSolicitante>
<ans:nomeProfissional>Luis Otavio Martins Todesco</ans:nomeProfissional>
<ans:conselhoProfissional>06</ans:conselhoProfissional>
<ans:numeroConselhoProfissional>226604</ans:numeroConselhoProfissional>
<ans:UF>35</ans:UF>
<ans:CBOS>225125</ans:CBOS>
</ans:profissionalSolicitante>
</ans:dadosSolicitante>
<ans:dadosSolicitacao>
<ans:dataSolicitacao>2025-09-30</ans:dataSolicitacao>
<ans:caraterAtendimento>2</ans:caraterAtendimento>
<ans:indicacaoClinica>OUTRAS DORES ABDOMINAIS E AS NAO ESPECIFICADAS</ans:indicacaoClinica>
</ans:dadosSolicitacao>
<ans:dadosExecutante>
<ans:contratadoExecutante>
<ans:codigoPrestadorNaOperadora>110020</ans:codigoPrestadorNaOperadora>
</ans:contratadoExecutante>
<ans:CNES>2097117</ans:CNES>
</ans:dadosExecutante>
<ans:dadosAtendimento>
<ans:tipoAtendimento>04</ans:tipoAtendimento>
<ans:indicacaoAcidente>9</ans:indicacaoAcidente>
<ans:tipoConsulta>1</ans:tipoConsulta>
<ans:regimeAtendimento>04</ans:regimeAtendimento>
</ans:dadosAtendimento>
<ans:procedimentosExecutados>
<ans:procedimentoExecutado>
<ans:sequencialItem>1</ans:sequencialItem>
<ans:dataExecucao>2025-09-30</ans:dataExecucao>
<ans:horaInicial>10:52:38</ans:horaInicial>
<ans:horaFinal>10:52:38</ans:horaFinal>
<ans:procedimento>
<ans:codigoTabela>98</ans:codigoTabela>
<ans:codigoProcedimento>98200709</ans:codigoProcedimento>
<ans:descricaoProcedimento>Consulta De Urgencia Global</ans:descricaoProcedimento>
</ans:procedimento>
<ans:quantidadeExecutada>1</ans:quantidadeExecutada>
<ans:viaAcesso>1</ans:viaAcesso>
<ans:tecnicaUtilizada>1</ans:tecnicaUtilizada>
<ans:reducaoAcrescimo>1.00</ans:reducaoAcrescimo>
<ans:valorUnitario>69.00</ans:valorUnitario>
<ans:valorTotal>69.00</ans:valorTotal>
<ans:equipeSadt>
<ans:grauPart>12</ans:grauPart>
<ans:codProfissional>
<ans:codigoPrestadorNaOperadora>110020</ans:codigoPrestadorNaOperadora>
</ans:codProfissional>
<ans:nomeProf>Ronaldo Gonçalves Da Silva</ans:nomeProf>
<ans:conselho>06</ans:conselho>
<ans:numeroConselhoProfissional>139120</ans:numeroConselhoProfissional>
<ans:UF>35</ans:UF>
<ans:CBOS>225125</ans:CBOS>
</ans:equipeSadt>
</ans:procedimentoExecutado>
<ans:procedimentoExecutado>
<ans:sequencialItem>2</ans:sequencialItem>
<ans:dataExecucao>2025-09-30</ans:dataExecucao>
<ans:horaInicial>11:56:02</ans:horaInicial>
<ans:horaFinal>11:56:02</ans:horaFinal>
<ans:procedimento>
<ans:codigoTabela>22</ans:codigoTabela>
<ans:codigoProcedimento>10101039</ans:codigoProcedimento>
<ans:descricaoProcedimento>Consulta Em Pronto Socorro</ans:descricaoProcedimento>
</ans:procedimento>
<ans:quantidadeExecutada>1</ans:quantidadeExecutada>
<ans:viaAcesso>1</ans:viaAcesso>
<ans:tecnicaUtilizada>1</ans:tecnicaUtilizada>
<ans:reducaoAcrescimo>1.00</ans:reducaoAcrescimo>
<ans:valorUnitario>115.42</ans:valorUnitario>
<ans:valorTotal>115.42</ans:valorTotal>
<ans:equipeSadt>
<ans:grauPart>12</ans:grauPart>
<ans:codProfissional>
<ans:cpfContratado>00000263739</ans:cpfContratado>
</ans:codProfissional>
<ans:nomeProf>Matheus Alberto Fogolin Elias</ans:nomeProf>
<ans:conselho>06</ans:conselho>
<ans:numeroConselhoProfissional>263739</ans:numeroConselhoProfissional>
<ans:UF>35</ans:UF>
<ans:CBOS>225125</ans:CBOS>
</ans:equipeSadt>
</ans:procedimentoExecutado>
</ans:procedimentosExecutados>
<ans:valorTotal>
<ans:valorProcedimentos>184.42</ans:valorProcedimentos>
<ans:valorTotalGeral>184.42</ans:valorTotalGeral>
</ans:valorTotal>
</ans:guiaSP-SADT>
<ans:guiaSP-SADT>
<ans:cabecalhoGuia>
<ans:registroANS>335100</ans:registroANS>
<ans:numeroGuiaPrestador>233965</ans:numeroGuiaPrestador>
<ans:guiaPrincipal>22-54030247</ans:guiaPrincipal>
</ans:cabecalhoGuia>
<ans:dadosAutorizacao>
<ans:numeroGuiaOperadora>22-54030247</ans:numeroGuiaOperadora>
<ans:dataAutorizacao>2025-09-30</ans:dataAutorizacao>
<ans:senha>22-54030247</ans:senha>
</ans:dadosAutorizacao>
<ans:dadosBeneficiario>
<ans:numeroCarteira>00302913800003005</ans:numeroCarteira>
<ans:atendimentoRN>N</ans:atendimentoRN>
</ans:dadosBeneficiario>
<ans:dadosSolicitante>
<ans:contratadoSolicitante>
<ans:codigoPrestadorNaOperadora>110020</ans:codigoPrestadorNaOperadora>
</ans:contratadoSolicitante>
<ans:nomeContratadoSolicitante>Centro Medico Rio Preto S.a</ans:nomeContratadoSolicitante>
<ans:profissionalSolicitante>
<ans:nomeProfissional>Matheus Alberto Fogolin Elias</ans:nomeProfissional>
<ans:conselhoProfissional>06</ans:conselhoProfissional>
<ans:numeroConselhoProfissional>263739</ans:numeroConselhoProfissional>
<ans:UF>35</ans:UF>
<ans:CBOS>225125</ans:CBOS>
</ans:profissionalSolicitante>
</ans:dadosSolicitante>
<ans:dadosSolicitacao>
<ans:dataSolicitacao>2025-09-30</ans:dataSolicitacao>
<ans:caraterAtendimento>2</ans:caraterAtendimento>
<ans:indicacaoClinica>DIARREIA E GASTROENTERITE DE ORIGEM INFECCIOSA PRESUMIVEL</ans:indicacaoClinica>
</ans:dadosSolicitacao>
<ans:dadosExecutante>
<ans:contratadoExecutante>
<ans:codigoPrestadorNaOperadora>110020</ans:codigoPrestadorNaOperadora>
</ans:contratadoExecutante>
<ans:CNES>2097117</ans:CNES>
</ans:dadosExecutante>
<ans:dadosAtendimento>
<ans:tipoAtendimento>04</ans:tipoAtendimento>
<ans:indicacaoAcidente>9</ans:indicacaoAcidente>
<ans:tipoConsulta>1</ans:tipoConsulta>
<ans:regimeAtendimento>04</ans:regimeAtendimento>
</ans:dadosAtendimento>
<ans:procedimentosExecutados>
<ans:procedimentoExecutado>
<ans:sequencialItem>1</ans:sequencialItem>
<ans:dataExecucao>2025-09-30</ans:dataExecucao>
<ans:horaInicial>07:59:37</ans:horaInicial>
<ans:horaFinal>07:59:37</ans:horaFinal>
<ans:procedimento>
<ans:codigoTabela>98</ans:codigoTabela>
<ans:codigoProcedimento>98200709</ans:codigoProcedimento>
<ans:descricaoProcedimento>Consulta De Urgencia Global</ans:descricaoProcedimento>
</ans:procedimento>
<ans:quantidadeExecutada>1</ans:quantidadeExecutada>
<ans:viaAcesso>1</ans:viaAcesso>
<ans:tecnicaUtilizada>1</ans:tecnicaUtilizada>
<ans:reducaoAcrescimo>1.00</ans:reducaoAcrescimo>
<ans:valorUnitario>69.00</ans:valorUnitario>
<ans:valorTotal>69.00</ans:valorTotal>
<ans:equipeSadt>
<ans:grauPart>12</ans:grauPart>
<ans:codProfissional>
<ans:codigoPrestadorNaOperadora>110020</ans:codigoPrestadorNaOperadora>
</ans:codProfissional>
<ans:nomeProf>Ronaldo Gonçalves Da Silva</ans:nomeProf>
<ans:conselho>06</ans:conselho>
<ans:numeroConselhoProfissional>139120</ans:numeroConselhoProfissional>
<ans:UF>35</ans:UF>
<ans:CBOS>225125</ans:CBOS>
</ans:equipeSadt>
</ans:procedimentoExecutado>
<ans:procedimentoExecutado>
<ans:sequencialItem>2</ans:sequencialItem>
<ans:dataExecucao>2025-09-30</ans:dataExecucao>
<ans:horaInicial>08:19:34</ans:horaInicial>
<ans:horaFinal>08:19:34</ans:horaFinal>
<ans:procedimento>
<ans:codigoTabela>22</ans:codigoTabela>
<ans:codigoProcedimento>10101039</ans:codigoProcedimento>
<ans:descricaoProcedimento>Consulta Em Pronto Socorro</ans:descricaoProcedimento>
</ans:procedimento>
<ans:quantidadeExecutada>1</ans:quantidadeExecutada>
<ans:viaAcesso>1</ans:viaAcesso>
<ans:tecnicaUtilizada>1</ans:tecnicaUtilizada>
<ans:reducaoAcrescimo>1.00</ans:reducaoAcrescimo>
<ans:valorUnitario>115.42</ans:valorUnitario>
<ans:valorTotal>115.42</ans:valorTotal>
<ans:equipeSadt>
<ans:grauPart>12</ans:grauPart>
<ans:codProfissional>
<ans:cpfContratado>00000263739</ans:cpfContratado>
</ans:codProfissional>
<ans:nomeProf>Matheus Alberto Fogolin Elias</ans:nomeProf>
<ans:conselho>06</ans:conselho>
<ans:numeroConselhoProfissional>263739</ans:numeroConselhoProfissional>
<ans:UF>35</ans:UF>
<ans:CBOS>225125</ans:CBOS>
</ans:equipeSadt>
</ans:procedimentoExecutado>
</ans:procedimentosExecutados>
<ans:valorTotal>
<ans:valorProcedimentos>184.42</ans:valorProcedimentos>
<ans:valorTotalGeral>184.42</ans:valorTotalGeral>
</ans:valorTotal>
</ans:guiaSP-SADT>
<ans:guiaSP-SADT>
<ans:cabecalhoGuia>
<ans:registroANS>335100</ans:registroANS>
<ans:numeroGuiaPrestador>234296</ans:numeroGuiaPrestador>
<ans:guiaPrincipal>22-54044012</ans:guiaPrincipal>
</ans:cabecalhoGuia>
<ans:dadosAutorizacao>
<ans:numeroGuiaOperadora>22-54044012</ans:numeroGuiaOperadora>
<ans:dataAutorizacao>2025-09-30</ans:dataAutorizacao>
<ans:senha>22-54044012</ans:senha>
</ans:dadosAutorizacao>
<ans:dadosBeneficiario>
<ans:numeroCarteira>00306016026687003</ans:numeroCarteira>
<ans:atendimentoRN>N</ans:atendimentoRN>
</ans:dadosBeneficiario>
<ans:dadosSolicitante>
<ans:contratadoSolicitante>
<ans:codigoPrestadorNaOperadora>110020</ans:codigoPrestadorNaOperadora>
</ans:contratadoSolicitante>
<ans:nomeContratadoSolicitante>Centro Medico Rio Preto S.a</ans:nomeContratadoSolicitante>
<ans:profissionalSolicitante>
<ans:nomeProfissional>Rafaella Maionchi Martins Fachin</ans:nomeProfissional>
<ans:conselhoProfissional>06</ans:conselhoProfissional>
<ans:numeroConselhoProfissional>138267</ans:numeroConselhoProfissional>
<ans:UF>35</ans:UF>
<ans:CBOS>225124</ans:CBOS>
</ans:profissionalSolicitante>
</ans:dadosSolicitante>
<ans:dadosSolicitacao>
<ans:dataSolicitacao>2025-09-30</ans:dataSolicitacao>
<ans:caraterAtendimento>2</ans:caraterAtendimento>
<ans:indicacaoClinica>DIARREIA E GASTROENTERITE DE ORIGEM INFECCIOSA PRESUMIVEL</ans:indicacaoClinica>
</ans:dadosSolicitacao>
<ans:dadosExecutante>
<ans:contratadoExecutante>
<ans:codigoPrestadorNaOperadora>110020</ans:codigoPrestadorNaOperadora>
</ans:contratadoExecutante>
<ans:CNES>2097117</ans:CNES>
</ans:dadosExecutante>
<ans:dadosAtendimento>
<ans:tipoAtendimento>04</ans:tipoAtendimento>
<ans:indicacaoAcidente>9</ans:indicacaoAcidente>
<ans:tipoConsulta>1</ans:tipoConsulta>
<ans:regimeAtendimento>04</ans:regimeAtendimento>
</ans:dadosAtendimento>
<ans:procedimentosExecutados>
<ans:procedimentoExecutado>
<ans:sequencialItem>1</ans:sequencialItem>
<ans:dataExecucao>2025-09-30</ans:dataExecucao>
<ans:horaInicial>13:23:16</ans:horaInicial>
<ans:horaFinal>13:23:16</ans:horaFinal>
<ans:procedimento>
<ans:codigoTabela>98</ans:codigoTabela>
<ans:codigoProcedimento>98200709</ans:codigoProcedimento>
<ans:descricaoProcedimento>Consulta De Urgencia Global</ans:descricaoProcedimento>
</ans:procedimento>
<ans:quantidadeExecutada>1</ans:quantidadeExecutada>
<ans:viaAcesso>1</ans:viaAcesso>
<ans:tecnicaUtilizada>1</ans:tecnicaUtilizada>
<ans:reducaoAcrescimo>1.00</ans:reducaoAcrescimo>
<ans:valorUnitario>69.00</ans:valorUnitario>
<ans:valorTotal>69.00</ans:valorTotal>
<ans:equipeSadt>
<ans:grauPart>12</ans:grauPart>
<ans:codProfissional>
<ans:codigoPrestadorNaOperadora>110020</ans:codigoPrestadorNaOperadora>
</ans:codProfissional>
<ans:nomeProf>Ronaldo Gonçalves Da Silva</ans:nomeProf>
<ans:conselho>06</ans:conselho>
<ans:numeroConselhoProfissional>139120</ans:numeroConselhoProfissional>
<ans:UF>35</ans:UF>
<ans:CBOS>225125</ans:CBOS>
</ans:equipeSadt>
</ans:procedimentoExecutado>
<ans:procedimentoExecutado>
<ans:sequencialItem>2</ans:sequencialItem>
<ans:dataExecucao>2025-09-30</ans:dataExecucao>
<ans:horaInicial>13:44:36</ans:horaInicial>
<ans:horaFinal>13:44:36</ans:horaFinal>
<ans:procedimento>
<ans:codigoTabela>22</ans:codigoTabela>
<ans:codigoProcedimento>10101039</ans:codigoProcedimento>
<ans:descricaoProcedimento>Consulta Em Pronto Socorro</ans:descricaoProcedimento>
</ans:procedimento>
<ans:quantidadeExecutada>1</ans:quantidadeExecutada>
<ans:viaAcesso>1</ans:viaAcesso>
<ans:tecnicaUtilizada>1</ans:tecnicaUtilizada>
<ans:reducaoAcrescimo>1.00</ans:reducaoAcrescimo>
<ans:valorUnitario>115.42</ans:valorUnitario>
<ans:valorTotal>115.42</ans:valorTotal>
<ans:equipeSadt>
<ans:grauPart>12</ans:grauPart>
<ans:codProfissional>
<ans:codigoPrestadorNaOperadora>110020</ans:codigoPrestadorNaOperadora>
</ans:codProfissional>
<ans:nomeProf>Rafaella Maionchi Martins Fachin</ans:nomeProf>
<ans:conselho>06</ans:conselho>
<ans:numeroConselhoProfissional>138267</ans:numeroConselhoProfissional>
<ans:UF>35</ans:UF>
<ans:CBOS>225124</ans:CBOS>
</ans:equipeSadt>
</ans:procedimentoExecutado>
</ans:procedimentosExecutados>
<ans:valorTotal>
<ans:valorProcedimentos>184.42</ans:valorProcedimentos>
<ans:valorTotalGeral>184.42</ans:valorTotalGeral>
</ans:valorTotal>
</ans:guiaSP-SADT>
<ans:guiaSP-SADT>
<ans:cabecalhoGuia>
<ans:registroANS>335100</ans:registroANS>
<ans:numeroGuiaPrestador>242132</ans:numeroGuiaPrestador>
<ans:guiaPrincipal>22-54281055</ans:guiaPrincipal>
</ans:cabecalhoGuia>
<ans:dadosAutorizacao>
<ans:numeroGuiaOperadora>22-54281055</ans:numeroGuiaOperadora>
<ans:dataAutorizacao>2025-10-12</ans:dataAutorizacao>
<ans:senha>22-54281055</ans:senha>
</ans:dadosAutorizacao>
<ans:dadosBeneficiario>
<ans:numeroCarteira>00302766601197002</ans:numeroCarteira>
<ans:atendimentoRN>N</ans:atendimentoRN>
</ans:dadosBeneficiario>
<ans:dadosSolicitante>
<ans:contratadoSolicitante>
<ans:codigoPrestadorNaOperadora>110020</ans:codigoPrestadorNaOperadora>
</ans:contratadoSolicitante>
<ans:nomeContratadoSolicitante>Centro Medico Rio Preto S.a</ans:nomeContratadoSolicitante>
<ans:profissionalSolicitante>
<ans:nomeProfissional>Andrey Jose Mamed Jordao</ans:nomeProfissional>
<ans:conselhoProfissional>06</ans:conselhoProfissional>
<ans:numeroConselhoProfissional>271637</ans:numeroConselhoProfissional>
<ans:UF>35</ans:UF>
<ans:CBOS>225260</ans:CBOS>
</ans:profissionalSolicitante>
</ans:dadosSolicitante>
<ans:dadosSolicitacao>
<ans:dataSolicitacao>2025-10-12</ans:dataSolicitacao>
<ans:caraterAtendimento>2</ans:caraterAtendimento>
<ans:indicacaoClinica>SINDROME DO TUNEL DO CARPO</ans:indicacaoClinica>
</ans:dadosSolicitacao>
<ans:dadosExecutante>
<ans:contratadoExecutante>
<ans:codigoPrestadorNaOperadora>110020</ans:codigoPrestadorNaOperadora>
</ans:contratadoExecutante>
<ans:CNES>2097117</ans:CNES>
</ans:dadosExecutante>
<ans:dadosAtendimento>
<ans:tipoAtendimento>04</ans:tipoAtendimento>
<ans:indicacaoAcidente>9</ans:indicacaoAcidente>
<ans:tipoConsulta>1</ans:tipoConsulta>
<ans:regimeAtendimento>04</ans:regimeAtendimento>
</ans:dadosAtendimento>
<ans:procedimentosExecutados>
<ans:procedimentoExecutado>
<ans:sequencialItem>1</ans:sequencialItem>
<ans:dataExecucao>2025-10-12</ans:dataExecucao>
<ans:horaInicial>01:43:31</ans:horaInicial>
<ans:horaFinal>01:43:31</ans:horaFinal>
<ans:procedimento>
<ans:codigoTabela>98</ans:codigoTabela>
<ans:codigoProcedimento>98200709</ans:codigoProcedimento>
<ans:descricaoProcedimento>Consulta De Urgencia Global</ans:descricaoProcedimento>
</ans:procedimento>
<ans:quantidadeExecutada>1</ans:quantidadeExecutada>
<ans:viaAcesso>1</ans:viaAcesso>
<ans:tecnicaUtilizada>1</ans:tecnicaUtilizada>
<ans:reducaoAcrescimo>1.00</ans:reducaoAcrescimo>
<ans:valorUnitario>69.00</ans:valorUnitario>
<ans:valorTotal>69.00</ans:valorTotal>
<ans:equipeSadt>
<ans:grauPart>12</ans:grauPart>
<ans:codProfissional>
<ans:codigoPrestadorNaOperadora>110020</ans:codigoPrestadorNaOperadora>
</ans:codProfissional>
<ans:nomeProf>Ronaldo Gonçalves Da Silva</ans:nomeProf>
<ans:conselho>06</ans:conselho>
<ans:numeroConselhoProfissional>139120</ans:numeroConselhoProfissional>
<ans:UF>35</ans:UF>
<ans:CBOS>225125</ans:CBOS>
</ans:equipeSadt>
</ans:procedimentoExecutado>
</ans:procedimentosExecutados>
<ans:valorTotal>
<ans:valorProcedimentos>69.00</ans:valorProcedimentos>
<ans:valorTotalGeral>69.00</ans:valorTotalGeral>
</ans:valorTotal>
</ans:guiaSP-SADT>
<ans:guiaSP-SADT>
<ans:cabecalhoGuia>
<ans:registroANS>335100</ans:registroANS>
<ans:numeroGuiaPrestador>242132</ans:numeroGuiaPrestador>
<ans:guiaPrincipal>22-54281055</ans:guiaPrincipal>
</ans:cabecalhoGuia>
<ans:dadosAutorizacao>
<ans:numeroGuiaOperadora>22-54281055</ans:numeroGuiaOperadora>
<ans:dataAutorizacao>2025-10-12</ans:dataAutorizacao>
<ans:senha>22-54281055</ans:senha>
</ans:dadosAutorizacao>
<ans:dadosBeneficiario>
<ans:numeroCarteira>00302766601197002</ans:numeroCarteira>
<ans:atendimentoRN>N</ans:atendimentoRN>
</ans:dadosBeneficiario>
<ans:dadosSolicitante>
<ans:contratadoSolicitante>
<ans:codigoPrestadorNaOperadora>110020</ans:codigoPrestadorNaOperadora>
</ans:contratadoSolicitante>
<ans:nomeContratadoSolicitante>Centro Medico Rio Preto S.a</ans:nomeContratadoSolicitante>
<ans:profissionalSolicitante>
<ans:nomeProfissional>Andrey Jose Mamed Jordao</ans:nomeProfissional>
<ans:conselhoProfissional>06</ans:conselhoProfissional>
<ans:numeroConselhoProfissional>271637</ans:numeroConselhoProfissional>
<ans:UF>35</ans:UF>
<ans:CBOS>225260</ans:CBOS>
</ans:profissionalSolicitante>
</ans:dadosSolicitante>
<ans:dadosSolicitacao>
<ans:dataSolicitacao>2025-10-12</ans:dataSolicitacao>
<ans:caraterAtendimento>2</ans:caraterAtendimento>
<ans:indicacaoClinica>SINDROME DO TUNEL DO CARPO</ans:indicacaoClinica>
</ans:dadosSolicitacao>
<ans:dadosExecutante>
<ans:contratadoExecutante>
<ans:codigoPrestadorNaOperadora>110020</ans:codigoPrestadorNaOperadora>
</ans:contratadoExecutante>
<ans:CNES>2097117</ans:CNES>
</ans:dadosExecutante>
<ans:dadosAtendimento>
<ans:tipoAtendimento>04</ans:tipoAtendimento>
<ans:indicacaoAcidente>9</ans:indicacaoAcidente><ans:tipoConsulta>1</ans:tipoConsulta>
<ans:regimeAtendimento>04</ans:regimeAtendimento>
</ans:dadosAtendimento>
<ans:procedimentosExecutados>
<ans:procedimentoExecutado>
<ans:sequencialItem>1</ans:sequencialItem>
<ans:dataExecucao>2025-10-12</ans:dataExecucao>
<ans:horaInicial>02:01:04</ans:horaInicial>
<ans:horaFinal>02:01:04</ans:horaFinal>
<ans:procedimento>
<ans:codigoTabela>22</ans:codigoTabela>
<ans:codigoProcedimento>10101039</ans:codigoProcedimento>
<ans:descricaoProcedimento>Consulta Em Pronto Socorro</ans:descricaoProcedimento>
</ans:procedimento>
<ans:quantidadeExecutada>1</ans:quantidadeExecutada>
<ans:viaAcesso>1</ans:viaAcesso>
<ans:tecnicaUtilizada>1</ans:tecnicaUtilizada>
<ans:reducaoAcrescimo>1.00</ans:reducaoAcrescimo>
<ans:valorUnitario>115.42</ans:valorUnitario>
<ans:valorTotal>115.42</ans:valorTotal>
<ans:equipeSadt>
<ans:grauPart>12</ans:grauPart>
<ans:codProfissional>
<ans:cpfContratado>00000271637</ans:cpfContratado>
</ans:codProfissional>
<ans:nomeProf>Andrey Jose Mamed Jordao</ans:nomeProf>
<ans:conselho>06</ans:conselho>
<ans:numeroConselhoProfissional>271637</ans:numeroConselhoProfissional>
<ans:UF>35</ans:UF>
<ans:CBOS>225260</ans:CBOS>
</ans:equipeSadt>
</ans:procedimentoExecutado>
</ans:procedimentosExecutados>
<ans:valorTotal>
<ans:valorProcedimentos>115.42</ans:valorProcedimentos>
<ans:valorTotalGeral>115.42</ans:valorTotalGeral>
</ans:valorTotal>
</ans:guiaSP-SADT>
<ans:guiaSP-SADT>
<ans:cabecalhoGuia>
<ans:registroANS>335100</ans:registroANS>
<ans:numeroGuiaPrestador>234235</ans:numeroGuiaPrestador>
<ans:guiaPrincipal>22-54039757</ans:guiaPrincipal>
</ans:cabecalhoGuia>
<ans:dadosAutorizacao>
<ans:numeroGuiaOperadora>22-54039757</ans:numeroGuiaOperadora>
<ans:dataAutorizacao>2025-09-30</ans:dataAutorizacao>
<ans:senha>22-54039757</ans:senha>
</ans:dadosAutorizacao>
<ans:dadosBeneficiario>
<ans:numeroCarteira>00306010019058110</ans:numeroCarteira>
<ans:atendimentoRN>N</ans:atendimentoRN>
</ans:dadosBeneficiario>
<ans:dadosSolicitante>
<ans:contratadoSolicitante>
<ans:codigoPrestadorNaOperadora>110020</ans:codigoPrestadorNaOperadora>
</ans:contratadoSolicitante>
<ans:nomeContratadoSolicitante>Centro Medico Rio Preto S.a</ans:nomeContratadoSolicitante>
<ans:profissionalSolicitante>
<ans:nomeProfissional>Matheus Alberto Fogolin Elias</ans:nomeProfissional>
<ans:conselhoProfissional>06</ans:conselhoProfissional>
<ans:numeroConselhoProfissional>263739</ans:numeroConselhoProfissional>
<ans:UF>35</ans:UF>
<ans:CBOS>225125</ans:CBOS>
</ans:profissionalSolicitante>
</ans:dadosSolicitante>
<ans:dadosSolicitacao>
<ans:dataSolicitacao>2025-09-30</ans:dataSolicitacao>
<ans:caraterAtendimento>2</ans:caraterAtendimento>
<ans:indicacaoClinica>DIARREIA E GASTROENTERITE DE ORIGEM INFECCIOSA PRESUMIVEL</ans:indicacaoClinica>
</ans:dadosSolicitacao>
<ans:dadosExecutante>
<ans:contratadoExecutante>
<ans:codigoPrestadorNaOperadora>110020</ans:codigoPrestadorNaOperadora>
</ans:contratadoExecutante>
<ans:CNES>2097117</ans:CNES>
</ans:dadosExecutante>
<ans:dadosAtendimento>
<ans:tipoAtendimento>04</ans:tipoAtendimento>
<ans:indicacaoAcidente>9</ans:indicacaoAcidente>
<ans:tipoConsulta>1</ans:tipoConsulta>
<ans:regimeAtendimento>04</ans:regimeAtendimento>
</ans:dadosAtendimento>
<ans:procedimentosExecutados>
<ans:procedimentoExecutado>
<ans:sequencialItem>1</ans:sequencialItem>
<ans:dataExecucao>2025-09-30</ans:dataExecucao>
<ans:horaInicial>10:40:06</ans:horaInicial>
<ans:horaFinal>10:40:06</ans:horaFinal>
<ans:procedimento>
<ans:codigoTabela>98</ans:codigoTabela>
<ans:codigoProcedimento>98200709</ans:codigoProcedimento>
<ans:descricaoProcedimento>Consulta De Urgencia Global</ans:descricaoProcedimento>
</ans:procedimento>
<ans:quantidadeExecutada>1</ans:quantidadeExecutada>
<ans:viaAcesso>1</ans:viaAcesso>
<ans:tecnicaUtilizada>1</ans:tecnicaUtilizada>
<ans:reducaoAcrescimo>1.00</ans:reducaoAcrescimo>
<ans:valorUnitario>69.00</ans:valorUnitario>
<ans:valorTotal>69.00</ans:valorTotal>
<ans:equipeSadt>
<ans:grauPart>12</ans:grauPart>
<ans:codProfissional>
<ans:codigoPrestadorNaOperadora>110020</ans:codigoPrestadorNaOperadora>
</ans:codProfissional>
<ans:nomeProf>Ronaldo Gonçalves Da Silva</ans:nomeProf>
<ans:conselho>06</ans:conselho>
<ans:numeroConselhoProfissional>139120</ans:numeroConselhoProfissional>
<ans:UF>35</ans:UF>
<ans:CBOS>225125</ans:CBOS>
</ans:equipeSadt>
</ans:procedimentoExecutado>
<ans:procedimentoExecutado>
<ans:sequencialItem>2</ans:sequencialItem>
<ans:dataExecucao>2025-09-30</ans:dataExecucao>
<ans:horaInicial>11:30:30</ans:horaInicial>
<ans:horaFinal>11:30:30</ans:horaFinal>
<ans:procedimento>
<ans:codigoTabela>22</ans:codigoTabela>
<ans:codigoProcedimento>10101039</ans:codigoProcedimento>
<ans:descricaoProcedimento>Consulta Em Pronto Socorro</ans:descricaoProcedimento>
</ans:procedimento>
<ans:quantidadeExecutada>1</ans:quantidadeExecutada>
<ans:viaAcesso>1</ans:viaAcesso>
<ans:tecnicaUtilizada>1</ans:tecnicaUtilizada>
<ans:reducaoAcrescimo>1.00</ans:reducaoAcrescimo>
<ans:valorUnitario>115.42</ans:valorUnitario>
<ans:valorTotal>115.42</ans:valorTotal>
<ans:equipeSadt>
<ans:grauPart>12</ans:grauPart>
<ans:codProfissional>
<ans:cpfContratado>00000263739</ans:cpfContratado>
</ans:codProfissional>
<ans:nomeProf>Matheus Alberto Fogolin Elias</ans:nomeProf>
<ans:conselho>06</ans:conselho>
<ans:numeroConselhoProfissional>263739</ans:numeroConselhoProfissional>
<ans:UF>35</ans:UF>
<ans:CBOS>225125</ans:CBOS>
</ans:equipeSadt>
</ans:procedimentoExecutado>
</ans:procedimentosExecutados>
<ans:valorTotal>
<ans:valorProcedimentos>184.42</ans:valorProcedimentos>
<ans:valorTotalGeral>184.42</ans:valorTotalGeral>
</ans:valorTotal>
</ans:guiaSP-SADT>
<ans:guiaSP-SADT>
<ans:cabecalhoGuia>
<ans:registroANS>335100</ans:registroANS>
<ans:numeroGuiaPrestador>242311</ans:numeroGuiaPrestador>
<ans:guiaPrincipal>22-54282643</ans:guiaPrincipal>
</ans:cabecalhoGuia>
<ans:dadosAutorizacao>
<ans:numeroGuiaOperadora>22-54282643</ans:numeroGuiaOperadora>
<ans:dataAutorizacao>2025-10-12</ans:dataAutorizacao>
<ans:senha>22-54282643</ans:senha>
</ans:dadosAutorizacao>
<ans:dadosBeneficiario>
<ans:numeroCarteira>00306410099538004</ans:numeroCarteira>
<ans:atendimentoRN>N</ans:atendimentoRN>
</ans:dadosBeneficiario>
<ans:dadosSolicitante>
<ans:contratadoSolicitante>
<ans:codigoPrestadorNaOperadora>110020</ans:codigoPrestadorNaOperadora>
</ans:contratadoSolicitante>
<ans:nomeContratadoSolicitante>Centro Medico Rio Preto S.a</ans:nomeContratadoSolicitante>
<ans:profissionalSolicitante>
<ans:nomeProfissional>Andrey Jose Mamed Jordao</ans:nomeProfissional>
<ans:conselhoProfissional>06</ans:conselhoProfissional>
<ans:numeroConselhoProfissional>271637</ans:numeroConselhoProfissional>
<ans:UF>35</ans:UF>
<ans:CBOS>225260</ans:CBOS>
</ans:profissionalSolicitante>
</ans:dadosSolicitante>
<ans:dadosSolicitacao>
<ans:dataSolicitacao>2025-10-12</ans:dataSolicitacao>
<ans:caraterAtendimento>2</ans:caraterAtendimento>
<ans:indicacaoClinica>DIARREIA E GASTROENTERITE DE ORIGEM INFECCIOSA PRESUMIVEL</ans:indicacaoClinica>
</ans:dadosSolicitacao>
<ans:dadosExecutante>
<ans:contratadoExecutante>
<ans:codigoPrestadorNaOperadora>110020</ans:codigoPrestadorNaOperadora>
</ans:contratadoExecutante>
<ans:CNES>2097117</ans:CNES>
</ans:dadosExecutante>
<ans:dadosAtendimento>
<ans:tipoAtendimento>04</ans:tipoAtendimento>
<ans:indicacaoAcidente>9</ans:indicacaoAcidente>
<ans:tipoConsulta>1</ans:tipoConsulta>
<ans:regimeAtendimento>04</ans:regimeAtendimento>
</ans:dadosAtendimento>
<ans:procedimentosExecutados>
<ans:procedimentoExecutado>
<ans:sequencialItem>1</ans:sequencialItem>
<ans:dataExecucao>2025-10-12</ans:dataExecucao>
<ans:horaInicial>21:47:25</ans:horaInicial>
<ans:horaFinal>21:47:25</ans:horaFinal>
<ans:procedimento>
<ans:codigoTabela>98</ans:codigoTabela>
<ans:codigoProcedimento>98200709</ans:codigoProcedimento>
<ans:descricaoProcedimento>Consulta De Urgencia Global</ans:descricaoProcedimento>
</ans:procedimento>
<ans:quantidadeExecutada>1</ans:quantidadeExecutada>
<ans:viaAcesso>1</ans:viaAcesso>
<ans:tecnicaUtilizada>1</ans:tecnicaUtilizada>
<ans:reducaoAcrescimo>1.00</ans:reducaoAcrescimo>
<ans:valorUnitario>69.00</ans:valorUnitario>
<ans:valorTotal>69.00</ans:valorTotal>
<ans:equipeSadt>
<ans:grauPart>12</ans:grauPart>
<ans:codProfissional>
<ans:codigoPrestadorNaOperadora>110020</ans:codigoPrestadorNaOperadora>
</ans:codProfissional>
<ans:nomeProf>Ronaldo Gonçalves Da Silva</ans:nomeProf>
<ans:conselho>06</ans:conselho>
<ans:numeroConselhoProfissional>139120</ans:numeroConselhoProfissional>
<ans:UF>35</ans:UF>
<ans:CBOS>225125</ans:CBOS>
</ans:equipeSadt>
</ans:procedimentoExecutado>
</ans:procedimentosExecutados>
<ans:valorTotal>
<ans:valorProcedimentos>69.00</ans:valorProcedimentos>
<ans:valorTotalGeral>69.00</ans:valorTotalGeral>
</ans:valorTotal>
</ans:guiaSP-SADT>
<ans:guiaSP-SADT>
<ans:cabecalhoGuia>
<ans:registroANS>335100</ans:registroANS>
<ans:numeroGuiaPrestador>242311</ans:numeroGuiaPrestador>
<ans:guiaPrincipal>22-54282643</ans:guiaPrincipal>
</ans:cabecalhoGuia>
<ans:dadosAutorizacao>
<ans:numeroGuiaOperadora>22-54282643</ans:numeroGuiaOperadora>
<ans:dataAutorizacao>2025-10-12</ans:dataAutorizacao>
<ans:senha>22-54282643</ans:senha>
</ans:dadosAutorizacao>
<ans:dadosBeneficiario>
<ans:numeroCarteira>00306410099538004</ans:numeroCarteira>
<ans:atendimentoRN>N</ans:atendimentoRN>
</ans:dadosBeneficiario>
<ans:dadosSolicitante>
<ans:contratadoSolicitante>
<ans:codigoPrestadorNaOperadora>110020</ans:codigoPrestadorNaOperadora>
</ans:contratadoSolicitante>
<ans:nomeContratadoSolicitante>Centro Medico Rio Preto S.a</ans:nomeContratadoSolicitante>
<ans:profissionalSolicitante>
<ans:nomeProfissional>Andrey Jose Mamed Jordao</ans:nomeProfissional>
<ans:conselhoProfissional>06</ans:conselhoProfissional>
<ans:numeroConselhoProfissional>271637</ans:numeroConselhoProfissional>
<ans:UF>35</ans:UF>
<ans:CBOS>225260</ans:CBOS>
</ans:profissionalSolicitante>
</ans:dadosSolicitante>
<ans:dadosSolicitacao>
<ans:dataSolicitacao>2025-10-12</ans:dataSolicitacao>
<ans:caraterAtendimento>2</ans:caraterAtendimento>
<ans:indicacaoClinica>DIARREIA E GASTROENTERITE DE ORIGEM INFECCIOSA PRESUMIVEL</ans:indicacaoClinica>
</ans:dadosSolicitacao>
<ans:dadosExecutante>
<ans:contratadoExecutante>
<ans:codigoPrestadorNaOperadora>110020</ans:codigoPrestadorNaOperadora>
</ans:contratadoExecutante>
<ans:CNES>2097117</ans:CNES>
</ans:dadosExecutante>
<ans:dadosAtendimento>
<ans:tipoAtendimento>04</ans:tipoAtendimento>
<ans:indicacaoAcidente>9</ans:indicacaoAcidente>
<ans:tipoConsulta>1</ans:tipoConsulta>
<ans:regimeAtendimento>04</ans:regimeAtendimento>
</ans:dadosAtendimento>
<ans:procedimentosExecutados>
<ans:procedimentoExecutado>
<ans:sequencialItem>1</ans:sequencialItem>
<ans:dataExecucao>2025-10-12</ans:dataExecucao>
<ans:horaInicial>22:16:25</ans:horaInicial>
<ans:horaFinal>22:16:25</ans:horaFinal>
<ans:procedimento>
<ans:codigoTabela>22</ans:codigoTabela>
<ans:codigoProcedimento>10101039</ans:codigoProcedimento>
<ans:descricaoProcedimento>Consulta Em Pronto Socorro</ans:descricaoProcedimento>
</ans:procedimento>
<ans:quantidadeExecutada>1</ans:quantidadeExecutada>
<ans:viaAcesso>1</ans:viaAcesso>
<ans:tecnicaUtilizada>1</ans:tecnicaUtilizada>
<ans:reducaoAcrescimo>1.00</ans:reducaoAcrescimo>
<ans:valorUnitario>115.42</ans:valorUnitario>
<ans:valorTotal>115.42</ans:valorTotal>
<ans:equipeSadt>
<ans:grauPart>12</ans:grauPart>
<ans:codProfissional>
<ans:cpfContratado>00000271637</ans:cpfContratado>
</ans:codProfissional>
<ans:nomeProf>Andrey Jose Mamed Jordao</ans:nomeProf>
<ans:conselho>06</ans:conselho>
<ans:numeroConselhoProfissional>271637</ans:numeroConselhoProfissional>
<ans:UF>35</ans:UF>
<ans:CBOS>225260</ans:CBOS>
</ans:equipeSadt>
</ans:procedimentoExecutado>
</ans:procedimentosExecutados>
<ans:valorTotal>
<ans:valorProcedimentos>115.42</ans:valorProcedimentos>
<ans:valorTotalGeral>115.42</ans:valorTotalGeral>
</ans:valorTotal>
</ans:guiaSP-SADT>
<ans:guiaSP-SADT>
<ans:cabecalhoGuia>
<ans:registroANS>335100</ans:registroANS>
<ans:numeroGuiaPrestador>241459</ans:numeroGuiaPrestador>
<ans:guiaPrincipal>23-54274294</ans:guiaPrincipal>
</ans:cabecalhoGuia>
<ans:dadosAutorizacao>
<ans:numeroGuiaOperadora>23-54274294</ans:numeroGuiaOperadora>
<ans:dataAutorizacao>2025-10-10</ans:dataAutorizacao>
<ans:senha>23-54274294</ans:senha>
</ans:dadosAutorizacao>
<ans:dadosBeneficiario>
<ans:numeroCarteira>09942627527326000</ans:numeroCarteira>
<ans:atendimentoRN>N</ans:atendimentoRN>
</ans:dadosBeneficiario>
<ans:dadosSolicitante>
<ans:contratadoSolicitante>
<ans:codigoPrestadorNaOperadora>110020</ans:codigoPrestadorNaOperadora>
</ans:contratadoSolicitante>
<ans:nomeContratadoSolicitante>Centro Medico Rio Preto S.a</ans:nomeContratadoSolicitante>
<ans:profissionalSolicitante>
<ans:nomeProfissional>Ana Laura Martins Todesco</ans:nomeProfissional>
<ans:conselhoProfissional>06</ans:conselhoProfissional>
<ans:numeroConselhoProfissional>200980</ans:numeroConselhoProfissional>
<ans:UF>35</ans:UF>
<ans:CBOS>225125</ans:CBOS>
</ans:profissionalSolicitante>
</ans:dadosSolicitante>
<ans:dadosSolicitacao>
<ans:dataSolicitacao>2025-10-10</ans:dataSolicitacao>
<ans:caraterAtendimento>2</ans:caraterAtendimento>
<ans:indicacaoClinica>COLICA NEFRETICA NAO ESPECIFICADA</ans:indicacaoClinica>
</ans:dadosSolicitacao>
<ans:dadosExecutante>
<ans:contratadoExecutante>
<ans:codigoPrestadorNaOperadora>110020</ans:codigoPrestadorNaOperadora>
</ans:contratadoExecutante>
<ans:CNES>2097117</ans:CNES>
</ans:dadosExecutante>
<ans:dadosAtendimento>
<ans:tipoAtendimento>04</ans:tipoAtendimento>
<ans:indicacaoAcidente>9</ans:indicacaoAcidente>
<ans:tipoConsulta>1</ans:tipoConsulta>
<ans:regimeAtendimento>04</ans:regimeAtendimento>
</ans:dadosAtendimento>
<ans:procedimentosExecutados>
<ans:procedimentoExecutado>
<ans:sequencialItem>1</ans:sequencialItem>
<ans:dataExecucao>2025-10-10</ans:dataExecucao>
<ans:horaInicial>16:50:21</ans:horaInicial>
<ans:horaFinal>16:50:21</ans:horaFinal>
<ans:procedimento>
<ans:codigoTabela>98</ans:codigoTabela>
<ans:codigoProcedimento>98200709</ans:codigoProcedimento>
<ans:descricaoProcedimento>Consulta De Urgencia Global</ans:descricaoProcedimento>
</ans:procedimento>
<ans:quantidadeExecutada>1</ans:quantidadeExecutada>
<ans:viaAcesso>1</ans:viaAcesso>
<ans:tecnicaUtilizada>1</ans:tecnicaUtilizada>
<ans:reducaoAcrescimo>1.00</ans:reducaoAcrescimo>
<ans:valorUnitario>99.08</ans:valorUnitario>
<ans:valorTotal>99.08</ans:valorTotal>
<ans:equipeSadt>
<ans:grauPart>12</ans:grauPart>
<ans:codProfissional>
<ans:codigoPrestadorNaOperadora>110020</ans:codigoPrestadorNaOperadora>
</ans:codProfissional>
<ans:nomeProf>Ronaldo Gonçalves Da Silva</ans:nomeProf>
<ans:conselho>06</ans:conselho>
<ans:numeroConselhoProfissional>139120</ans:numeroConselhoProfissional>
<ans:UF>35</ans:UF>
<ans:CBOS>225125</ans:CBOS>
</ans:equipeSadt>
</ans:procedimentoExecutado>
<ans:procedimentoExecutado>
<ans:sequencialItem>2</ans:sequencialItem>
<ans:dataExecucao>2025-10-10</ans:dataExecucao>
<ans:horaInicial>17:10:00</ans:horaInicial>
<ans:horaFinal>17:10:00</ans:horaFinal>
<ans:procedimento>
<ans:codigoTabela>22</ans:codigoTabela>
<ans:codigoProcedimento>10101039</ans:codigoProcedimento>
<ans:descricaoProcedimento>Consulta Em Pronto Socorro</ans:descricaoProcedimento>
</ans:procedimento>
<ans:quantidadeExecutada>1</ans:quantidadeExecutada>
<ans:viaAcesso>1</ans:viaAcesso>
<ans:tecnicaUtilizada>1</ans:tecnicaUtilizada>
<ans:reducaoAcrescimo>1.00</ans:reducaoAcrescimo>
<ans:valorUnitario>85.35</ans:valorUnitario>
<ans:valorTotal>85.35</ans:valorTotal>
<ans:equipeSadt>
<ans:grauPart>12</ans:grauPart>
<ans:codProfissional>
<ans:cpfContratado>00000270768</ans:cpfContratado>
</ans:codProfissional>
<ans:nomeProf>Gilberto Gomes da Silveira</ans:nomeProf>
<ans:conselho>06</ans:conselho>
<ans:numeroConselhoProfissional>270768</ans:numeroConselhoProfissional>
<ans:UF>35</ans:UF>
<ans:CBOS>225125</ans:CBOS>
</ans:equipeSadt>
</ans:procedimentoExecutado>
</ans:procedimentosExecutados>
<ans:valorTotal>
<ans:valorProcedimentos>184.43</ans:valorProcedimentos>
<ans:valorTotalGeral>184.43</ans:valorTotalGeral>
</ans:valorTotal>
</ans:guiaSP-SADT>
<ans:guiaSP-SADT>
<ans:cabecalhoGuia>
<ans:registroANS>335100</ans:registroANS>
<ans:numeroGuiaPrestador>242815</ans:numeroGuiaPrestador>
<ans:guiaPrincipal>22-54298137</ans:guiaPrincipal>
</ans:cabecalhoGuia>
<ans:dadosAutorizacao>
<ans:numeroGuiaOperadora>22-54298137</ans:numeroGuiaOperadora>
<ans:dataAutorizacao>2025-10-13</ans:dataAutorizacao>
<ans:senha>22-54298137</ans:senha>
</ans:dadosAutorizacao>
<ans:dadosBeneficiario>
<ans:numeroCarteira>00306014025597004</ans:numeroCarteira>
<ans:atendimentoRN>N</ans:atendimentoRN>
</ans:dadosBeneficiario>
<ans:dadosSolicitante>
<ans:contratadoSolicitante>
<ans:codigoPrestadorNaOperadora>110020</ans:codigoPrestadorNaOperadora>
</ans:contratadoSolicitante>
<ans:nomeContratadoSolicitante>Centro Medico Rio Preto S.a</ans:nomeContratadoSolicitante>
<ans:profissionalSolicitante>
<ans:nomeProfissional>Andrey Jose Mamed Jordao</ans:nomeProfissional>
<ans:conselhoProfissional>06</ans:conselhoProfissional>
<ans:numeroConselhoProfissional>271637</ans:numeroConselhoProfissional>
<ans:UF>35</ans:UF>
<ans:CBOS>225260</ans:CBOS>
</ans:profissionalSolicitante>
</ans:dadosSolicitante>
<ans:dadosSolicitacao>
<ans:dataSolicitacao>2025-10-13</ans:dataSolicitacao>
<ans:caraterAtendimento>2</ans:caraterAtendimento>
<ans:indicacaoClinica>CEFALEIA</ans:indicacaoClinica>
</ans:dadosSolicitacao>
<ans:dadosExecutante>
<ans:contratadoExecutante>
<ans:codigoPrestadorNaOperadora>110020</ans:codigoPrestadorNaOperadora>
</ans:contratadoExecutante>
<ans:CNES>2097117</ans:CNES>
</ans:dadosExecutante>
<ans:dadosAtendimento>
<ans:tipoAtendimento>04</ans:tipoAtendimento>
<ans:indicacaoAcidente>9</ans:indicacaoAcidente>
<ans:tipoConsulta>1</ans:tipoConsulta>
<ans:regimeAtendimento>04</ans:regimeAtendimento>
</ans:dadosAtendimento>
<ans:procedimentosExecutados>
<ans:procedimentoExecutado>
<ans:sequencialItem>1</ans:sequencialItem>
<ans:dataExecucao>2025-10-13</ans:dataExecucao>
<ans:horaInicial>13:53:16</ans:horaInicial>
<ans:horaFinal>13:53:16</ans:horaFinal>
<ans:procedimento>
<ans:codigoTabela>98</ans:codigoTabela>
<ans:codigoProcedimento>98200709</ans:codigoProcedimento>
<ans:descricaoProcedimento>Consulta De Urgencia Global</ans:descricaoProcedimento>
</ans:procedimento>
<ans:quantidadeExecutada>1</ans:quantidadeExecutada>
<ans:viaAcesso>1</ans:viaAcesso>
<ans:tecnicaUtilizada>1</ans:tecnicaUtilizada>
<ans:reducaoAcrescimo>1.00</ans:reducaoAcrescimo>
<ans:valorUnitario>69.00</ans:valorUnitario>
<ans:valorTotal>69.00</ans:valorTotal>
<ans:equipeSadt>
<ans:grauPart>12</ans:grauPart>
<ans:codProfissional>
<ans:codigoPrestadorNaOperadora>110020</ans:codigoPrestadorNaOperadora>
</ans:codProfissional>
<ans:nomeProf>Ronaldo Gonçalves Da Silva</ans:nomeProf>
<ans:conselho>06</ans:conselho>
<ans:numeroConselhoProfissional>139120</ans:numeroConselhoProfissional>
<ans:UF>35</ans:UF>
<ans:CBOS>225125</ans:CBOS>
</ans:equipeSadt>
</ans:procedimentoExecutado>
<ans:procedimentoExecutado>
<ans:sequencialItem>2</ans:sequencialItem>
<ans:dataExecucao>2025-10-13</ans:dataExecucao>
<ans:horaInicial>14:50:44</ans:horaInicial>
<ans:horaFinal>14:50:44</ans:horaFinal>
<ans:procedimento>
<ans:codigoTabela>22</ans:codigoTabela>
<ans:codigoProcedimento>10101039</ans:codigoProcedimento>
<ans:descricaoProcedimento>Consulta Em Pronto Socorro</ans:descricaoProcedimento>
</ans:procedimento>
<ans:quantidadeExecutada>1</ans:quantidadeExecutada>
<ans:viaAcesso>1</ans:viaAcesso>
<ans:tecnicaUtilizada>1</ans:tecnicaUtilizada>
<ans:reducaoAcrescimo>1.00</ans:reducaoAcrescimo>
<ans:valorUnitario>115.42</ans:valorUnitario>
<ans:valorTotal>115.42</ans:valorTotal>
<ans:equipeSadt>
<ans:grauPart>12</ans:grauPart>
<ans:codProfissional>
<ans:cpfContratado>00000271637</ans:cpfContratado>
</ans:codProfissional>
<ans:nomeProf>Andrey Jose Mamed Jordao</ans:nomeProf>
<ans:conselho>06</ans:conselho>
<ans:numeroConselhoProfissional>271637</ans:numeroConselhoProfissional>
<ans:UF>35</ans:UF>
<ans:CBOS>225260</ans:CBOS>
</ans:equipeSadt>
</ans:procedimentoExecutado>
</ans:procedimentosExecutados>
<ans:valorTotal>
<ans:valorProcedimentos>184.42</ans:valorProcedimentos>
<ans:valorTotalGeral>184.42</ans:valorTotalGeral>
</ans:valorTotal>
</ans:guiaSP-SADT>
<ans:guiaSP-SADT>
<ans:cabecalhoGuia>
<ans:registroANS>335100</ans:registroANS>
<ans:numeroGuiaPrestador>242036</ans:numeroGuiaPrestador>
<ans:guiaPrincipal>22-54280455</ans:guiaPrincipal>
</ans:cabecalhoGuia>
<ans:dadosAutorizacao>
<ans:numeroGuiaOperadora>22-54280455</ans:numeroGuiaOperadora>
<ans:dataAutorizacao>2025-10-11</ans:dataAutorizacao>
<ans:senha>22-54280455</ans:senha>
</ans:dadosAutorizacao>
<ans:dadosBeneficiario>
<ans:numeroCarteira>00306000004150000</ans:numeroCarteira>
<ans:atendimentoRN>N</ans:atendimentoRN>
</ans:dadosBeneficiario>
<ans:dadosSolicitante>
<ans:contratadoSolicitante>
<ans:codigoPrestadorNaOperadora>110020</ans:codigoPrestadorNaOperadora>
</ans:contratadoSolicitante>
<ans:nomeContratadoSolicitante>Centro Medico Rio Preto S.a</ans:nomeContratadoSolicitante>
<ans:profissionalSolicitante>
<ans:nomeProfissional>Fabio Stucchi Devito Filho</ans:nomeProfissional>
<ans:conselhoProfissional>06</ans:conselhoProfissional>
<ans:numeroConselhoProfissional>218324</ans:numeroConselhoProfissional>
<ans:UF>35</ans:UF>
<ans:CBOS>225270</ans:CBOS>
</ans:profissionalSolicitante>
</ans:dadosSolicitante>
<ans:dadosSolicitacao>
<ans:dataSolicitacao>2025-10-11</ans:dataSolicitacao>
<ans:caraterAtendimento>2</ans:caraterAtendimento>
<ans:indicacaoClinica>FRATURA DO PUBIS</ans:indicacaoClinica>
</ans:dadosSolicitacao>
<ans:dadosExecutante>
<ans:contratadoExecutante>
<ans:codigoPrestadorNaOperadora>110020</ans:codigoPrestadorNaOperadora>
</ans:contratadoExecutante>
<ans:CNES>2097117</ans:CNES>
</ans:dadosExecutante>
<ans:dadosAtendimento>
<ans:tipoAtendimento>04</ans:tipoAtendimento>
<ans:indicacaoAcidente>9</ans:indicacaoAcidente>
<ans:tipoConsulta>1</ans:tipoConsulta>
<ans:regimeAtendimento>04</ans:regimeAtendimento>
</ans:dadosAtendimento>
<ans:procedimentosExecutados>
<ans:procedimentoExecutado>
<ans:sequencialItem>1</ans:sequencialItem>
<ans:dataExecucao>2025-10-11</ans:dataExecucao>
<ans:horaInicial>17:12:47</ans:horaInicial>
<ans:horaFinal>17:12:47</ans:horaFinal>
<ans:procedimento>
<ans:codigoTabela>98</ans:codigoTabela>
<ans:codigoProcedimento>98200709</ans:codigoProcedimento>
<ans:descricaoProcedimento>Consulta De Urgencia Global</ans:descricaoProcedimento>
</ans:procedimento>
<ans:quantidadeExecutada>1</ans:quantidadeExecutada>
<ans:viaAcesso>1</ans:viaAcesso>
<ans:tecnicaUtilizada>1</ans:tecnicaUtilizada>
<ans:reducaoAcrescimo>1.00</ans:reducaoAcrescimo>
<ans:valorUnitario>69.00</ans:valorUnitario>
<ans:valorTotal>69.00</ans:valorTotal>
<ans:equipeSadt>
<ans:grauPart>12</ans:grauPart>
<ans:codProfissional>
<ans:codigoPrestadorNaOperadora>110020</ans:codigoPrestadorNaOperadora>
</ans:codProfissional>
<ans:nomeProf>Ronaldo Gonçalves Da Silva</ans:nomeProf>
<ans:conselho>06</ans:conselho>
<ans:numeroConselhoProfissional>139120</ans:numeroConselhoProfissional>
<ans:UF>35</ans:UF>
<ans:CBOS>225125</ans:CBOS>
</ans:equipeSadt>
</ans:procedimentoExecutado>
</ans:procedimentosExecutados>
<ans:valorTotal>
<ans:valorProcedimentos>69.00</ans:valorProcedimentos>
<ans:valorTotalGeral>69.00</ans:valorTotalGeral>
</ans:valorTotal>
</ans:guiaSP-SADT>
<ans:guiaSP-SADT>
<ans:cabecalhoGuia>
<ans:registroANS>335100</ans:registroANS>
<ans:numeroGuiaPrestador>242036</ans:numeroGuiaPrestador>
<ans:guiaPrincipal>22-54280455</ans:guiaPrincipal>
</ans:cabecalhoGuia>
<ans:dadosAutorizacao>
<ans:numeroGuiaOperadora>22-54280455</ans:numeroGuiaOperadora>
<ans:dataAutorizacao>2025-10-11</ans:dataAutorizacao>
<ans:senha>22-54280455</ans:senha>
</ans:dadosAutorizacao>
<ans:dadosBeneficiario>
<ans:numeroCarteira>00306000004150000</ans:numeroCarteira>
<ans:atendimentoRN>N</ans:atendimentoRN>
</ans:dadosBeneficiario>
<ans:dadosSolicitante>
<ans:contratadoSolicitante>
<ans:codigoPrestadorNaOperadora>110020</ans:codigoPrestadorNaOperadora>
</ans:contratadoSolicitante>
<ans:nomeContratadoSolicitante>Centro Medico Rio Preto S.a</ans:nomeContratadoSolicitante>
<ans:profissionalSolicitante>
<ans:nomeProfissional>Fabio Stucchi Devito Filho</ans:nomeProfissional>
<ans:conselhoProfissional>06</ans:conselhoProfissional>
<ans:numeroConselhoProfissional>218324</ans:numeroConselhoProfissional>
<ans:UF>35</ans:UF>
<ans:CBOS>225270</ans:CBOS>
</ans:profissionalSolicitante>
</ans:dadosSolicitante>
<ans:dadosSolicitacao>
<ans:dataSolicitacao>2025-10-11</ans:dataSolicitacao>
<ans:caraterAtendimento>2</ans:caraterAtendimento>
<ans:indicacaoClinica>ps</ans:indicacaoClinica>
</ans:dadosSolicitacao>
<ans:dadosExecutante>
<ans:contratadoExecutante>
<ans:codigoPrestadorNaOperadora>110020</ans:codigoPrestadorNaOperadora>
</ans:contratadoExecutante>
<ans:CNES>2097117</ans:CNES>
</ans:dadosExecutante>
<ans:dadosAtendimento>
<ans:tipoAtendimento>04</ans:tipoAtendimento>
<ans:indicacaoAcidente>9</ans:indicacaoAcidente>
<ans:tipoConsulta>1</ans:tipoConsulta>
<ans:regimeAtendimento>04</ans:regimeAtendimento>
</ans:dadosAtendimento>
<ans:procedimentosExecutados>
<ans:procedimentoExecutado>
<ans:sequencialItem>1</ans:sequencialItem>
<ans:dataExecucao>2025-10-11</ans:dataExecucao>
<ans:horaInicial>17:27:37</ans:horaInicial>
<ans:horaFinal>17:27:37</ans:horaFinal>
<ans:procedimento>
<ans:codigoTabela>22</ans:codigoTabela>
<ans:codigoProcedimento>10101039</ans:codigoProcedimento>
<ans:descricaoProcedimento>Consulta Em Pronto Socorro</ans:descricaoProcedimento>
</ans:procedimento>
<ans:quantidadeExecutada>1</ans:quantidadeExecutada>
<ans:viaAcesso>1</ans:viaAcesso>
<ans:tecnicaUtilizada>1</ans:tecnicaUtilizada>
<ans:reducaoAcrescimo>1.00</ans:reducaoAcrescimo>
<ans:valorUnitario>115.42</ans:valorUnitario>
<ans:valorTotal>115.42</ans:valorTotal>
<ans:equipeSadt>
<ans:grauPart>12</ans:grauPart>
<ans:codProfissional>
<ans:cpfContratado>00000271637</ans:cpfContratado>
</ans:codProfissional>
<ans:nomeProf>Andrey Jose Mamed Jordao</ans:nomeProf>
<ans:conselho>06</ans:conselho>
<ans:numeroConselhoProfissional>271637</ans:numeroConselhoProfissional>
<ans:UF>35</ans:UF>
<ans:CBOS>225260</ans:CBOS>
</ans:equipeSadt>
</ans:procedimentoExecutado>
</ans:procedimentosExecutados>
<ans:valorTotal>
<ans:valorProcedimentos>115.42</ans:valorProcedimentos>
<ans:valorTotalGeral>115.42</ans:valorTotalGeral>
</ans:valorTotal>
</ans:guiaSP-SADT>
<ans:guiaSP-SADT>
<ans:cabecalhoGuia>
<ans:registroANS>335100</ans:registroANS>
<ans:numeroGuiaPrestador>241501</ans:numeroGuiaPrestador>
<ans:guiaPrincipal>22-54275317</ans:guiaPrincipal>
</ans:cabecalhoGuia>
<ans:dadosAutorizacao>
<ans:numeroGuiaOperadora>22-54275317</ans:numeroGuiaOperadora>
<ans:dataAutorizacao>2025-10-10</ans:dataAutorizacao>
<ans:senha>22-54275317</ans:senha>
</ans:dadosAutorizacao>
<ans:dadosBeneficiario>
<ans:numeroCarteira>00306414012131007</ans:numeroCarteira>
<ans:atendimentoRN>N</ans:atendimentoRN>
</ans:dadosBeneficiario>
<ans:dadosSolicitante>
<ans:contratadoSolicitante>
<ans:codigoPrestadorNaOperadora>110020</ans:codigoPrestadorNaOperadora>
</ans:contratadoSolicitante>
<ans:nomeContratadoSolicitante>Centro Medico Rio Preto S.a</ans:nomeContratadoSolicitante>
<ans:profissionalSolicitante>
<ans:nomeProfissional>Bruna Gossn Ferraz Parolari</ans:nomeProfissional>
<ans:conselhoProfissional>06</ans:conselhoProfissional>
<ans:numeroConselhoProfissional>184302</ans:numeroConselhoProfissional>
<ans:UF>35</ans:UF>
<ans:CBOS>225125</ans:CBOS>
</ans:profissionalSolicitante>
</ans:dadosSolicitante>
<ans:dadosSolicitacao>
<ans:dataSolicitacao>2025-10-10</ans:dataSolicitacao>
<ans:caraterAtendimento>2</ans:caraterAtendimento>
<ans:indicacaoClinica>INFECCAO AGUDA DAS VIAS AEREAS SUPERIORES NAO ESPECIFICADA</ans:indicacaoClinica>
</ans:dadosSolicitacao>
<ans:dadosExecutante>
<ans:contratadoExecutante>
<ans:codigoPrestadorNaOperadora>110020</ans:codigoPrestadorNaOperadora>
</ans:contratadoExecutante>
<ans:CNES>2097117</ans:CNES>
</ans:dadosExecutante>
<ans:dadosAtendimento>
<ans:tipoAtendimento>04</ans:tipoAtendimento>
<ans:indicacaoAcidente>9</ans:indicacaoAcidente>
<ans:tipoConsulta>1</ans:tipoConsulta>
<ans:regimeAtendimento>04</ans:regimeAtendimento>
</ans:dadosAtendimento>
<ans:procedimentosExecutados>
<ans:procedimentoExecutado>
<ans:sequencialItem>1</ans:sequencialItem>
<ans:dataExecucao>2025-10-10</ans:dataExecucao>
<ans:horaInicial>18:38:02</ans:horaInicial>
<ans:horaFinal>18:38:02</ans:horaFinal>
<ans:procedimento>
<ans:codigoTabela>22</ans:codigoTabela>
<ans:codigoProcedimento>10101039</ans:codigoProcedimento>
<ans:descricaoProcedimento>Consulta Em Pronto Socorro</ans:descricaoProcedimento>
</ans:procedimento>
<ans:quantidadeExecutada>1</ans:quantidadeExecutada>
<ans:viaAcesso>1</ans:viaAcesso>
<ans:tecnicaUtilizada>1</ans:tecnicaUtilizada>
<ans:reducaoAcrescimo>1.00</ans:reducaoAcrescimo>
<ans:valorUnitario>115.42</ans:valorUnitario>
<ans:valorTotal>115.42</ans:valorTotal>
<ans:equipeSadt>
<ans:grauPart>12</ans:grauPart>
<ans:codProfissional>
<ans:codigoPrestadorNaOperadora>110020</ans:codigoPrestadorNaOperadora>
</ans:codProfissional>
<ans:nomeProf>Bruna Gossn Ferraz Parolari</ans:nomeProf>
<ans:conselho>06</ans:conselho>
<ans:numeroConselhoProfissional>184302</ans:numeroConselhoProfissional>
<ans:UF>35</ans:UF>
<ans:CBOS>225125</ans:CBOS>
</ans:equipeSadt>
</ans:procedimentoExecutado>
</ans:procedimentosExecutados>
<ans:valorTotal>
<ans:valorProcedimentos>115.42</ans:valorProcedimentos>
<ans:valorTotalGeral>115.42</ans:valorTotalGeral>
</ans:valorTotal>
</ans:guiaSP-SADT>
<ans:guiaSP-SADT>
<ans:cabecalhoGuia>
<ans:registroANS>335100</ans:registroANS>
<ans:numeroGuiaPrestador>241501</ans:numeroGuiaPrestador>
<ans:guiaPrincipal>22-54275317</ans:guiaPrincipal>
</ans:cabecalhoGuia>
<ans:dadosAutorizacao>
<ans:numeroGuiaOperadora>22-54275317</ans:numeroGuiaOperadora>
<ans:dataAutorizacao>2025-10-10</ans:dataAutorizacao>
<ans:senha>22-54275317</ans:senha>
</ans:dadosAutorizacao>
<ans:dadosBeneficiario>
<ans:numeroCarteira>00306414012131007</ans:numeroCarteira>
<ans:atendimentoRN>N</ans:atendimentoRN>
</ans:dadosBeneficiario>
<ans:dadosSolicitante>
<ans:contratadoSolicitante>
<ans:codigoPrestadorNaOperadora>110020</ans:codigoPrestadorNaOperadora>
</ans:contratadoSolicitante>
<ans:nomeContratadoSolicitante>Centro Medico Rio Preto S.a</ans:nomeContratadoSolicitante>
<ans:profissionalSolicitante>
<ans:nomeProfissional>Bruna Gossn Ferraz Parolari</ans:nomeProfissional>
<ans:conselhoProfissional>06</ans:conselhoProfissional>
<ans:numeroConselhoProfissional>184302</ans:numeroConselhoProfissional>
<ans:UF>35</ans:UF>
<ans:CBOS>225125</ans:CBOS>
</ans:profissionalSolicitante>
</ans:dadosSolicitante>
<ans:dadosSolicitacao>
<ans:dataSolicitacao>2025-10-10</ans:dataSolicitacao>
<ans:caraterAtendimento>2</ans:caraterAtendimento>
<ans:indicacaoClinica>INFECCAO AGUDA DAS VIAS AEREAS SUPERIORES NAO ESPECIFICADA</ans:indicacaoClinica>
</ans:dadosSolicitacao>
<ans:dadosExecutante>
<ans:contratadoExecutante><ans:codigoPrestadorNaOperadora>110020</ans:codigoPrestadorNaOperadora>
</ans:contratadoExecutante>
<ans:CNES>2097117</ans:CNES>
</ans:dadosExecutante>
<ans:dadosAtendimento>
<ans:tipoAtendimento>04</ans:tipoAtendimento>
<ans:indicacaoAcidente>9</ans:indicacaoAcidente>
<ans:tipoConsulta>1</ans:tipoConsulta>
<ans:regimeAtendimento>04</ans:regimeAtendimento>
</ans:dadosAtendimento>
<ans:procedimentosExecutados>
<ans:procedimentoExecutado>
<ans:sequencialItem>1</ans:sequencialItem>
<ans:dataExecucao>2025-10-10</ans:dataExecucao>
<ans:horaInicial>18:16:39</ans:horaInicial>
<ans:horaFinal>18:16:39</ans:horaFinal>
<ans:procedimento>
<ans:codigoTabela>98</ans:codigoTabela>
<ans:codigoProcedimento>98200709</ans:codigoProcedimento>
<ans:descricaoProcedimento>Consulta De Urgencia Global</ans:descricaoProcedimento>
</ans:procedimento>
<ans:quantidadeExecutada>1</ans:quantidadeExecutada>
<ans:viaAcesso>1</ans:viaAcesso>
<ans:tecnicaUtilizada>1</ans:tecnicaUtilizada>
<ans:reducaoAcrescimo>1.00</ans:reducaoAcrescimo>
<ans:valorUnitario>69.00</ans:valorUnitario>
<ans:valorTotal>69.00</ans:valorTotal>
<ans:equipeSadt>
<ans:grauPart>12</ans:grauPart>
<ans:codProfissional>
<ans:codigoPrestadorNaOperadora>110020</ans:codigoPrestadorNaOperadora>
</ans:codProfissional>
<ans:nomeProf>Ronaldo Gonçalves Da Silva</ans:nomeProf>
<ans:conselho>06</ans:conselho>
<ans:numeroConselhoProfissional>139120</ans:numeroConselhoProfissional>
<ans:UF>35</ans:UF>
<ans:CBOS>225125</ans:CBOS>
</ans:equipeSadt>
</ans:procedimentoExecutado>
</ans:procedimentosExecutados>
<ans:valorTotal>
<ans:valorProcedimentos>69.00</ans:valorProcedimentos>
<ans:valorTotalGeral>69.00</ans:valorTotalGeral>
</ans:valorTotal>
</ans:guiaSP-SADT>
<ans:guiaSP-SADT>
<ans:cabecalhoGuia>
<ans:registroANS>335100</ans:registroANS>
<ans:numeroGuiaPrestador>241958</ans:numeroGuiaPrestador>
<ans:guiaPrincipal>22-54279972</ans:guiaPrincipal>
</ans:cabecalhoGuia>
<ans:dadosAutorizacao>
<ans:numeroGuiaOperadora>22-54279972</ans:numeroGuiaOperadora>
<ans:dataAutorizacao>2025-10-11</ans:dataAutorizacao>
<ans:senha>22-54279972</ans:senha>
</ans:dadosAutorizacao>
<ans:dadosBeneficiario>
<ans:numeroCarteira>00302086000079005</ans:numeroCarteira>
<ans:atendimentoRN>N</ans:atendimentoRN>
</ans:dadosBeneficiario>
<ans:dadosSolicitante>
<ans:contratadoSolicitante>
<ans:codigoPrestadorNaOperadora>110020</ans:codigoPrestadorNaOperadora>
</ans:contratadoSolicitante>
<ans:nomeContratadoSolicitante>Centro Medico Rio Preto S.a</ans:nomeContratadoSolicitante>
<ans:profissionalSolicitante>
<ans:nomeProfissional>Andrey Jose Mamed Jordao</ans:nomeProfissional>
<ans:conselhoProfissional>06</ans:conselhoProfissional>
<ans:numeroConselhoProfissional>271637</ans:numeroConselhoProfissional>
<ans:UF>35</ans:UF>
<ans:CBOS>225260</ans:CBOS>
</ans:profissionalSolicitante>
</ans:dadosSolicitante>
<ans:dadosSolicitacao>
<ans:dataSolicitacao>2025-10-11</ans:dataSolicitacao>
<ans:caraterAtendimento>2</ans:caraterAtendimento>
<ans:indicacaoClinica>TOSSE</ans:indicacaoClinica>
</ans:dadosSolicitacao>
<ans:dadosExecutante>
<ans:contratadoExecutante>
<ans:codigoPrestadorNaOperadora>110020</ans:codigoPrestadorNaOperadora>
</ans:contratadoExecutante>
<ans:CNES>2097117</ans:CNES>
</ans:dadosExecutante>
<ans:dadosAtendimento>
<ans:tipoAtendimento>04</ans:tipoAtendimento>
<ans:indicacaoAcidente>9</ans:indicacaoAcidente>
<ans:tipoConsulta>1</ans:tipoConsulta>
<ans:regimeAtendimento>04</ans:regimeAtendimento>
</ans:dadosAtendimento>
<ans:procedimentosExecutados>
<ans:procedimentoExecutado>
<ans:sequencialItem>1</ans:sequencialItem>
<ans:dataExecucao>2025-10-11</ans:dataExecucao>
<ans:horaInicial>12:54:29</ans:horaInicial>
<ans:horaFinal>12:54:29</ans:horaFinal>
<ans:procedimento>
<ans:codigoTabela>98</ans:codigoTabela>
<ans:codigoProcedimento>98200709</ans:codigoProcedimento>
<ans:descricaoProcedimento>Consulta De Urgencia Global</ans:descricaoProcedimento>
</ans:procedimento>
<ans:quantidadeExecutada>1</ans:quantidadeExecutada>
<ans:viaAcesso>1</ans:viaAcesso>
<ans:tecnicaUtilizada>1</ans:tecnicaUtilizada>
<ans:reducaoAcrescimo>1.00</ans:reducaoAcrescimo>
<ans:valorUnitario>69.00</ans:valorUnitario>
<ans:valorTotal>69.00</ans:valorTotal>
<ans:equipeSadt>
<ans:grauPart>12</ans:grauPart>
<ans:codProfissional>
<ans:codigoPrestadorNaOperadora>110020</ans:codigoPrestadorNaOperadora>
</ans:codProfissional>
<ans:nomeProf>Ronaldo Gonçalves Da Silva</ans:nomeProf>
<ans:conselho>06</ans:conselho>
<ans:numeroConselhoProfissional>139120</ans:numeroConselhoProfissional>
<ans:UF>35</ans:UF>
<ans:CBOS>225125</ans:CBOS>
</ans:equipeSadt>
</ans:procedimentoExecutado>
</ans:procedimentosExecutados>
<ans:valorTotal>
<ans:valorProcedimentos>69.00</ans:valorProcedimentos>
<ans:valorTotalGeral>69.00</ans:valorTotalGeral>
</ans:valorTotal>
</ans:guiaSP-SADT>
<ans:guiaSP-SADT>
<ans:cabecalhoGuia>
<ans:registroANS>335100</ans:registroANS>
<ans:numeroGuiaPrestador>241958</ans:numeroGuiaPrestador>
<ans:guiaPrincipal>22-54279972</ans:guiaPrincipal>
</ans:cabecalhoGuia>
<ans:dadosAutorizacao>
<ans:numeroGuiaOperadora>22-54279972</ans:numeroGuiaOperadora>
<ans:dataAutorizacao>2025-10-11</ans:dataAutorizacao>
<ans:senha>22-54279972</ans:senha>
</ans:dadosAutorizacao>
<ans:dadosBeneficiario>
<ans:numeroCarteira>00302086000079005</ans:numeroCarteira>
<ans:atendimentoRN>N</ans:atendimentoRN>
</ans:dadosBeneficiario>
<ans:dadosSolicitante>
<ans:contratadoSolicitante>
<ans:codigoPrestadorNaOperadora>110020</ans:codigoPrestadorNaOperadora>
</ans:contratadoSolicitante>
<ans:nomeContratadoSolicitante>Centro Medico Rio Preto S.a</ans:nomeContratadoSolicitante>
<ans:profissionalSolicitante>
<ans:nomeProfissional>Andrey Jose Mamed Jordao</ans:nomeProfissional>
<ans:conselhoProfissional>06</ans:conselhoProfissional>
<ans:numeroConselhoProfissional>271637</ans:numeroConselhoProfissional>
<ans:UF>35</ans:UF>
<ans:CBOS>225260</ans:CBOS>
</ans:profissionalSolicitante>
</ans:dadosSolicitante>
<ans:dadosSolicitacao>
<ans:dataSolicitacao>2025-10-11</ans:dataSolicitacao>
<ans:caraterAtendimento>2</ans:caraterAtendimento>
<ans:indicacaoClinica>TOSSE</ans:indicacaoClinica>
</ans:dadosSolicitacao>
<ans:dadosExecutante>
<ans:contratadoExecutante>
<ans:codigoPrestadorNaOperadora>110020</ans:codigoPrestadorNaOperadora>
</ans:contratadoExecutante>
<ans:CNES>2097117</ans:CNES>
</ans:dadosExecutante>
<ans:dadosAtendimento>
<ans:tipoAtendimento>04</ans:tipoAtendimento>
<ans:indicacaoAcidente>9</ans:indicacaoAcidente>
<ans:tipoConsulta>1</ans:tipoConsulta>
<ans:regimeAtendimento>04</ans:regimeAtendimento>
</ans:dadosAtendimento>
<ans:procedimentosExecutados>
<ans:procedimentoExecutado>
<ans:sequencialItem>1</ans:sequencialItem>
<ans:dataExecucao>2025-10-11</ans:dataExecucao>
<ans:horaInicial>13:38:52</ans:horaInicial>
<ans:horaFinal>13:38:52</ans:horaFinal>
<ans:procedimento>
<ans:codigoTabela>22</ans:codigoTabela>
<ans:codigoProcedimento>10101039</ans:codigoProcedimento>
<ans:descricaoProcedimento>Consulta Em Pronto Socorro</ans:descricaoProcedimento>
</ans:procedimento>
<ans:quantidadeExecutada>1</ans:quantidadeExecutada>
<ans:viaAcesso>1</ans:viaAcesso>
<ans:tecnicaUtilizada>1</ans:tecnicaUtilizada>
<ans:reducaoAcrescimo>1.00</ans:reducaoAcrescimo>
<ans:valorUnitario>115.42</ans:valorUnitario>
<ans:valorTotal>115.42</ans:valorTotal>
<ans:equipeSadt>
<ans:grauPart>12</ans:grauPart>
<ans:codProfissional>
<ans:cpfContratado>00000271637</ans:cpfContratado>
</ans:codProfissional>
<ans:nomeProf>Andrey Jose Mamed Jordao</ans:nomeProf>
<ans:conselho>06</ans:conselho>
<ans:numeroConselhoProfissional>271637</ans:numeroConselhoProfissional>
<ans:UF>35</ans:UF>
<ans:CBOS>225260</ans:CBOS>
</ans:equipeSadt>
</ans:procedimentoExecutado>
</ans:procedimentosExecutados>
<ans:valorTotal>
<ans:valorProcedimentos>115.42</ans:valorProcedimentos>
<ans:valorTotalGeral>115.42</ans:valorTotalGeral>
</ans:valorTotal>
</ans:guiaSP-SADT>
<ans:guiaSP-SADT>
<ans:cabecalhoGuia>
<ans:registroANS>335100</ans:registroANS>
<ans:numeroGuiaPrestador>233982</ans:numeroGuiaPrestador>
<ans:guiaPrincipal>23-54042896</ans:guiaPrincipal>
</ans:cabecalhoGuia>
<ans:dadosAutorizacao>
<ans:numeroGuiaOperadora>23-54042896</ans:numeroGuiaOperadora>
<ans:dataAutorizacao>2025-09-30</ans:dataAutorizacao>
<ans:senha>23-54042896</ans:senha>
</ans:dadosAutorizacao>
<ans:dadosBeneficiario>
<ans:numeroCarteira>08650004812310011</ans:numeroCarteira>
<ans:atendimentoRN>N</ans:atendimentoRN>
</ans:dadosBeneficiario>
<ans:dadosSolicitante>
<ans:contratadoSolicitante>
<ans:codigoPrestadorNaOperadora>110020</ans:codigoPrestadorNaOperadora>
</ans:contratadoSolicitante>
<ans:nomeContratadoSolicitante>Centro Medico Rio Preto S.a</ans:nomeContratadoSolicitante>
<ans:profissionalSolicitante>
<ans:nomeProfissional>Matheus Alberto Fogolin Elias</ans:nomeProfissional>
<ans:conselhoProfissional>06</ans:conselhoProfissional>
<ans:numeroConselhoProfissional>263739</ans:numeroConselhoProfissional>
<ans:UF>35</ans:UF>
<ans:CBOS>225125</ans:CBOS>
</ans:profissionalSolicitante>
</ans:dadosSolicitante>
<ans:dadosSolicitacao>
<ans:dataSolicitacao>2025-09-30</ans:dataSolicitacao>
<ans:caraterAtendimento>2</ans:caraterAtendimento>
<ans:indicacaoClinica>INFLUENZA (GRIPE) DEVIDA A VIRUS NAO IDENTIFICADO</ans:indicacaoClinica>
</ans:dadosSolicitacao>
<ans:dadosExecutante>
<ans:contratadoExecutante>
<ans:codigoPrestadorNaOperadora>110020</ans:codigoPrestadorNaOperadora>
</ans:contratadoExecutante>
<ans:CNES>2097117</ans:CNES>
</ans:dadosExecutante>
<ans:dadosAtendimento>
<ans:tipoAtendimento>04</ans:tipoAtendimento>
<ans:indicacaoAcidente>9</ans:indicacaoAcidente>
<ans:tipoConsulta>1</ans:tipoConsulta>
<ans:regimeAtendimento>04</ans:regimeAtendimento>
</ans:dadosAtendimento>
<ans:procedimentosExecutados>
<ans:procedimentoExecutado>
<ans:sequencialItem>1</ans:sequencialItem>
<ans:dataExecucao>2025-09-30</ans:dataExecucao>
<ans:horaInicial>08:02:35</ans:horaInicial>
<ans:horaFinal>08:02:35</ans:horaFinal>
<ans:procedimento>
<ans:codigoTabela>98</ans:codigoTabela>
<ans:codigoProcedimento>98200709</ans:codigoProcedimento>
<ans:descricaoProcedimento>Consulta De Urgencia Global</ans:descricaoProcedimento>
</ans:procedimento>
<ans:quantidadeExecutada>1</ans:quantidadeExecutada>
<ans:viaAcesso>1</ans:viaAcesso>
<ans:tecnicaUtilizada>1</ans:tecnicaUtilizada>
<ans:reducaoAcrescimo>1.00</ans:reducaoAcrescimo>
<ans:valorUnitario>99.08</ans:valorUnitario>
<ans:valorTotal>99.08</ans:valorTotal>
<ans:equipeSadt>
<ans:grauPart>12</ans:grauPart>
<ans:codProfissional>
<ans:codigoPrestadorNaOperadora>110020</ans:codigoPrestadorNaOperadora>
</ans:codProfissional>
<ans:nomeProf>Ronaldo Gonçalves Da Silva</ans:nomeProf>
<ans:conselho>06</ans:conselho>
<ans:numeroConselhoProfissional>139120</ans:numeroConselhoProfissional>
<ans:UF>35</ans:UF>
<ans:CBOS>225125</ans:CBOS>
</ans:equipeSadt>
</ans:procedimentoExecutado>
<ans:procedimentoExecutado>
<ans:sequencialItem>2</ans:sequencialItem>
<ans:dataExecucao>2025-09-30</ans:dataExecucao>
<ans:horaInicial>08:28:19</ans:horaInicial>
<ans:horaFinal>08:28:19</ans:horaFinal>
<ans:procedimento>
<ans:codigoTabela>22</ans:codigoTabela>
<ans:codigoProcedimento>10101039</ans:codigoProcedimento>
<ans:descricaoProcedimento>Consulta Em Pronto Socorro</ans:descricaoProcedimento>
</ans:procedimento>
<ans:quantidadeExecutada>1</ans:quantidadeExecutada>
<ans:viaAcesso>1</ans:viaAcesso>
<ans:tecnicaUtilizada>1</ans:tecnicaUtilizada>
<ans:reducaoAcrescimo>1.00</ans:reducaoAcrescimo>
<ans:valorUnitario>85.35</ans:valorUnitario>
<ans:valorTotal>85.35</ans:valorTotal>
<ans:equipeSadt>
<ans:grauPart>12</ans:grauPart>
<ans:codProfissional>
<ans:cpfContratado>00000263739</ans:cpfContratado>
</ans:codProfissional>
<ans:nomeProf>Matheus Alberto Fogolin Elias</ans:nomeProf>
<ans:conselho>06</ans:conselho>
<ans:numeroConselhoProfissional>263739</ans:numeroConselhoProfissional>
<ans:UF>35</ans:UF>
<ans:CBOS>225125</ans:CBOS>
</ans:equipeSadt>
</ans:procedimentoExecutado>
</ans:procedimentosExecutados>
<ans:valorTotal>
<ans:valorProcedimentos>184.43</ans:valorProcedimentos>
<ans:valorTotalGeral>184.43</ans:valorTotalGeral>
</ans:valorTotal>
</ans:guiaSP-SADT>
<ans:guiaSP-SADT>
<ans:cabecalhoGuia>
<ans:registroANS>335100</ans:registroANS>
<ans:numeroGuiaPrestador>242110</ans:numeroGuiaPrestador>
<ans:guiaPrincipal>22-54280937</ans:guiaPrincipal>
</ans:cabecalhoGuia>
<ans:dadosAutorizacao>
<ans:numeroGuiaOperadora>22-54280937</ans:numeroGuiaOperadora>
<ans:dataAutorizacao>2025-10-11</ans:dataAutorizacao>
<ans:senha>22-54280937</ans:senha>
</ans:dadosAutorizacao>
<ans:dadosBeneficiario>
<ans:numeroCarteira>00307734000123003</ans:numeroCarteira>
<ans:atendimentoRN>N</ans:atendimentoRN>
</ans:dadosBeneficiario>
<ans:dadosSolicitante>
<ans:contratadoSolicitante>
<ans:codigoPrestadorNaOperadora>110020</ans:codigoPrestadorNaOperadora>
</ans:contratadoSolicitante>
<ans:nomeContratadoSolicitante>Centro Medico Rio Preto S.a</ans:nomeContratadoSolicitante>
<ans:profissionalSolicitante>
<ans:nomeProfissional>Andrey Jose Mamed Jordao</ans:nomeProfissional>
<ans:conselhoProfissional>06</ans:conselhoProfissional>
<ans:numeroConselhoProfissional>271637</ans:numeroConselhoProfissional>
<ans:UF>35</ans:UF>
<ans:CBOS>225260</ans:CBOS>
</ans:profissionalSolicitante>
</ans:dadosSolicitante>
<ans:dadosSolicitacao>
<ans:dataSolicitacao>2025-10-11</ans:dataSolicitacao>
<ans:caraterAtendimento>2</ans:caraterAtendimento>
<ans:indicacaoClinica>FERIMENTO DA PERNA, PARTE NAO ESPECIFICADA</ans:indicacaoClinica>
</ans:dadosSolicitacao>
<ans:dadosExecutante>
<ans:contratadoExecutante>
<ans:codigoPrestadorNaOperadora>110020</ans:codigoPrestadorNaOperadora>
</ans:contratadoExecutante>
<ans:CNES>2097117</ans:CNES>
</ans:dadosExecutante>
<ans:dadosAtendimento>
<ans:tipoAtendimento>04</ans:tipoAtendimento>
<ans:indicacaoAcidente>9</ans:indicacaoAcidente>
<ans:tipoConsulta>1</ans:tipoConsulta>
<ans:regimeAtendimento>04</ans:regimeAtendimento>
</ans:dadosAtendimento>
<ans:procedimentosExecutados>
<ans:procedimentoExecutado>
<ans:sequencialItem>1</ans:sequencialItem>
<ans:dataExecucao>2025-10-11</ans:dataExecucao>
<ans:horaInicial>22:35:57</ans:horaInicial>
<ans:horaFinal>22:35:57</ans:horaFinal>
<ans:procedimento>
<ans:codigoTabela>98</ans:codigoTabela>
<ans:codigoProcedimento>98200709</ans:codigoProcedimento>
<ans:descricaoProcedimento>Consulta De Urgencia Global</ans:descricaoProcedimento>
</ans:procedimento>
<ans:quantidadeExecutada>1</ans:quantidadeExecutada>
<ans:viaAcesso>1</ans:viaAcesso>
<ans:tecnicaUtilizada>1</ans:tecnicaUtilizada>
<ans:reducaoAcrescimo>1.00</ans:reducaoAcrescimo>
<ans:valorUnitario>69.00</ans:valorUnitario>
<ans:valorTotal>69.00</ans:valorTotal>
<ans:equipeSadt>
<ans:grauPart>12</ans:grauPart>
<ans:codProfissional>
<ans:codigoPrestadorNaOperadora>110020</ans:codigoPrestadorNaOperadora>
</ans:codProfissional>
<ans:nomeProf>Ronaldo Gonçalves Da Silva</ans:nomeProf>
<ans:conselho>06</ans:conselho>
<ans:numeroConselhoProfissional>139120</ans:numeroConselhoProfissional>
<ans:UF>35</ans:UF>
<ans:CBOS>225125</ans:CBOS>
</ans:equipeSadt>
</ans:procedimentoExecutado>
</ans:procedimentosExecutados>
<ans:valorTotal>
<ans:valorProcedimentos>69.00</ans:valorProcedimentos>
<ans:valorTotalGeral>69.00</ans:valorTotalGeral>
</ans:valorTotal>
</ans:guiaSP-SADT>
<ans:guiaSP-SADT>
<ans:cabecalhoGuia>
<ans:registroANS>335100</ans:registroANS>
<ans:numeroGuiaPrestador>242110</ans:numeroGuiaPrestador>
<ans:guiaPrincipal>22-54280937</ans:guiaPrincipal>
</ans:cabecalhoGuia>
<ans:dadosAutorizacao>
<ans:numeroGuiaOperadora>22-54280937</ans:numeroGuiaOperadora>
<ans:dataAutorizacao>2025-10-11</ans:dataAutorizacao>
<ans:senha>22-54280937</ans:senha>
</ans:dadosAutorizacao>
<ans:dadosBeneficiario>
<ans:numeroCarteira>00307734000123003</ans:numeroCarteira>
<ans:atendimentoRN>N</ans:atendimentoRN>
</ans:dadosBeneficiario>
<ans:dadosSolicitante>
<ans:contratadoSolicitante>
<ans:codigoPrestadorNaOperadora>110020</ans:codigoPrestadorNaOperadora>
</ans:contratadoSolicitante>
<ans:nomeContratadoSolicitante>Centro Medico Rio Preto S.a</ans:nomeContratadoSolicitante>
<ans:profissionalSolicitante>
<ans:nomeProfissional>Andrey Jose Mamed Jordao</ans:nomeProfissional>
<ans:conselhoProfissional>06</ans:conselhoProfissional>
<ans:numeroConselhoProfissional>271637</ans:numeroConselhoProfissional>
<ans:UF>35</ans:UF>
<ans:CBOS>225260</ans:CBOS>
</ans:profissionalSolicitante>
</ans:dadosSolicitante>
<ans:dadosSolicitacao>
<ans:dataSolicitacao>2025-10-11</ans:dataSolicitacao>
<ans:caraterAtendimento>2</ans:caraterAtendimento>
<ans:indicacaoClinica>FERIMENTO DA PERNA, PARTE NAO ESPECIFICADA</ans:indicacaoClinica>
</ans:dadosSolicitacao>
<ans:dadosExecutante>
<ans:contratadoExecutante>
<ans:codigoPrestadorNaOperadora>110020</ans:codigoPrestadorNaOperadora>
</ans:contratadoExecutante>
<ans:CNES>2097117</ans:CNES>
</ans:dadosExecutante>
<ans:dadosAtendimento>
<ans:tipoAtendimento>04</ans:tipoAtendimento>
<ans:indicacaoAcidente>9</ans:indicacaoAcidente>
<ans:tipoConsulta>1</ans:tipoConsulta>
<ans:regimeAtendimento>04</ans:regimeAtendimento>
</ans:dadosAtendimento>
<ans:procedimentosExecutados>
<ans:procedimentoExecutado>
<ans:sequencialItem>1</ans:sequencialItem>
<ans:dataExecucao>2025-10-11</ans:dataExecucao>
<ans:horaInicial>23:05:44</ans:horaInicial>
<ans:horaFinal>23:05:44</ans:horaFinal>
<ans:procedimento>
<ans:codigoTabela>22</ans:codigoTabela>
<ans:codigoProcedimento>10101039</ans:codigoProcedimento>
<ans:descricaoProcedimento>Consulta Em Pronto Socorro</ans:descricaoProcedimento>
</ans:procedimento>
<ans:quantidadeExecutada>1</ans:quantidadeExecutada>
<ans:viaAcesso>1</ans:viaAcesso>
<ans:tecnicaUtilizada>1</ans:tecnicaUtilizada>
<ans:reducaoAcrescimo>1.30</ans:reducaoAcrescimo>
<ans:valorUnitario>150.05</ans:valorUnitario>
<ans:valorTotal>150.05</ans:valorTotal>
<ans:equipeSadt>
<ans:grauPart>12</ans:grauPart>
<ans:codProfissional>
<ans:cpfContratado>00000271637</ans:cpfContratado>
</ans:codProfissional>
<ans:nomeProf>Andrey Jose Mamed Jordao</ans:nomeProf>
<ans:conselho>06</ans:conselho>
<ans:numeroConselhoProfissional>271637</ans:numeroConselhoProfissional>
<ans:UF>35</ans:UF>
<ans:CBOS>225260</ans:CBOS>
</ans:equipeSadt>
</ans:procedimentoExecutado>
</ans:procedimentosExecutados>
<ans:valorTotal>
<ans:valorProcedimentos>150.05</ans:valorProcedimentos>
<ans:valorTotalGeral>150.05</ans:valorTotalGeral>
</ans:valorTotal>
</ans:guiaSP-SADT>
<ans:guiaSP-SADT>
<ans:cabecalhoGuia>
<ans:registroANS>335100</ans:registroANS>
<ans:numeroGuiaPrestador>233899</ans:numeroGuiaPrestador>
<ans:guiaPrincipal>22-54028398</ans:guiaPrincipal>
</ans:cabecalhoGuia>
<ans:dadosAutorizacao>
<ans:numeroGuiaOperadora>22-54028398</ans:numeroGuiaOperadora>
<ans:dataAutorizacao>2025-09-30</ans:dataAutorizacao>
<ans:senha>22-54028398</ans:senha>
</ans:dadosAutorizacao>
<ans:dadosBeneficiario>
<ans:numeroCarteira>00306016015026019</ans:numeroCarteira>
<ans:atendimentoRN>N</ans:atendimentoRN>
</ans:dadosBeneficiario>
<ans:dadosSolicitante>
<ans:contratadoSolicitante>
<ans:codigoPrestadorNaOperadora>110020</ans:codigoPrestadorNaOperadora>
</ans:contratadoSolicitante>
<ans:nomeContratadoSolicitante>Centro Medico Rio Preto S.a</ans:nomeContratadoSolicitante>
<ans:profissionalSolicitante>
<ans:nomeProfissional>Matheus Alberto Fogolin Elias</ans:nomeProfissional>
<ans:conselhoProfissional>06</ans:conselhoProfissional>
<ans:numeroConselhoProfissional>263739</ans:numeroConselhoProfissional>
<ans:UF>35</ans:UF>
<ans:CBOS>225125</ans:CBOS>
</ans:profissionalSolicitante>
</ans:dadosSolicitante>
<ans:dadosSolicitacao>
<ans:dataSolicitacao>2025-09-30</ans:dataSolicitacao>
<ans:caraterAtendimento>2</ans:caraterAtendimento>
<ans:indicacaoClinica>OUTROS SANGRAMENTOS ANORMAIS DO UTERO E DA VAGINA</ans:indicacaoClinica>
</ans:dadosSolicitacao>
<ans:dadosExecutante>
<ans:contratadoExecutante>
<ans:codigoPrestadorNaOperadora>110020</ans:codigoPrestadorNaOperadora>
</ans:contratadoExecutante>
<ans:CNES>2097117</ans:CNES>
</ans:dadosExecutante>
<ans:dadosAtendimento>
<ans:tipoAtendimento>04</ans:tipoAtendimento>
<ans:indicacaoAcidente>9</ans:indicacaoAcidente>
<ans:tipoConsulta>1</ans:tipoConsulta>
<ans:regimeAtendimento>04</ans:regimeAtendimento>
</ans:dadosAtendimento>
<ans:procedimentosExecutados>
<ans:procedimentoExecutado>
<ans:sequencialItem>1</ans:sequencialItem>
<ans:dataExecucao>2025-09-30</ans:dataExecucao>
<ans:horaInicial>06:52:15</ans:horaInicial>
<ans:horaFinal>06:52:15</ans:horaFinal>
<ans:procedimento>
<ans:codigoTabela>98</ans:codigoTabela>
<ans:codigoProcedimento>98200709</ans:codigoProcedimento>
<ans:descricaoProcedimento>Consulta De Urgencia Global</ans:descricaoProcedimento>
</ans:procedimento>
<ans:quantidadeExecutada>1</ans:quantidadeExecutada>
<ans:viaAcesso>1</ans:viaAcesso>
<ans:tecnicaUtilizada>1</ans:tecnicaUtilizada>
<ans:reducaoAcrescimo>1.00</ans:reducaoAcrescimo>
<ans:valorUnitario>69.00</ans:valorUnitario>
<ans:valorTotal>69.00</ans:valorTotal>
<ans:equipeSadt>
<ans:grauPart>12</ans:grauPart>
<ans:codProfissional>
<ans:codigoPrestadorNaOperadora>110020</ans:codigoPrestadorNaOperadora>
</ans:codProfissional>
<ans:nomeProf>Ronaldo Gonçalves Da Silva</ans:nomeProf>
<ans:conselho>06</ans:conselho>
<ans:numeroConselhoProfissional>139120</ans:numeroConselhoProfissional>
<ans:UF>35</ans:UF>
<ans:CBOS>225125</ans:CBOS>
</ans:equipeSadt>
</ans:procedimentoExecutado>
<ans:procedimentoExecutado>
<ans:sequencialItem>2</ans:sequencialItem>
<ans:dataExecucao>2025-09-30</ans:dataExecucao>
<ans:horaInicial>07:22:00</ans:horaInicial>
<ans:horaFinal>07:22:00</ans:horaFinal>
<ans:procedimento>
<ans:codigoTabela>22</ans:codigoTabela>
<ans:codigoProcedimento>10101039</ans:codigoProcedimento>
<ans:descricaoProcedimento>Consulta Em Pronto Socorro</ans:descricaoProcedimento>
</ans:procedimento>
<ans:quantidadeExecutada>1</ans:quantidadeExecutada>
<ans:viaAcesso>1</ans:viaAcesso>
<ans:tecnicaUtilizada>1</ans:tecnicaUtilizada>
<ans:reducaoAcrescimo>1.00</ans:reducaoAcrescimo>
<ans:valorUnitario>115.42</ans:valorUnitario>
<ans:valorTotal>115.42</ans:valorTotal>
<ans:equipeSadt>
<ans:grauPart>12</ans:grauPart>
<ans:codProfissional>
<ans:cpfContratado>00000263739</ans:cpfContratado>
</ans:codProfissional>
<ans:nomeProf>Matheus Alberto Fogolin Elias</ans:nomeProf>
<ans:conselho>06</ans:conselho>
<ans:numeroConselhoProfissional>263739</ans:numeroConselhoProfissional>
<ans:UF>35</ans:UF>
<ans:CBOS>225125</ans:CBOS>
</ans:equipeSadt>
</ans:procedimentoExecutado>
</ans:procedimentosExecutados>
<ans:valorTotal>
<ans:valorProcedimentos>184.42</ans:valorProcedimentos>
<ans:valorTotalGeral>184.42</ans:valorTotalGeral>
</ans:valorTotal>
</ans:guiaSP-SADT>
<ans:guiaSP-SADT>
<ans:cabecalhoGuia>
<ans:registroANS>335100</ans:registroANS>
<ans:numeroGuiaPrestador>234398</ans:numeroGuiaPrestador>
<ans:guiaPrincipal>23-54049670</ans:guiaPrincipal>
</ans:cabecalhoGuia>
<ans:dadosAutorizacao>
<ans:numeroGuiaOperadora>23-54049670</ans:numeroGuiaOperadora>
<ans:dataAutorizacao>2025-09-30</ans:dataAutorizacao>
<ans:senha>23-54049670</ans:senha>
</ans:dadosAutorizacao>
<ans:dadosBeneficiario>
<ans:numeroCarteira>09942722102585000</ans:numeroCarteira>
<ans:atendimentoRN>N</ans:atendimentoRN>
</ans:dadosBeneficiario>
<ans:dadosSolicitante>
<ans:contratadoSolicitante>
<ans:codigoPrestadorNaOperadora>110020</ans:codigoPrestadorNaOperadora>
</ans:contratadoSolicitante>
<ans:nomeContratadoSolicitante>Centro Medico Rio Preto S.a</ans:nomeContratadoSolicitante>
<ans:profissionalSolicitante>
<ans:nomeProfissional>Matheus Alberto Fogolin Elias</ans:nomeProfissional>
<ans:conselhoProfissional>06</ans:conselhoProfissional>
<ans:numeroConselhoProfissional>263739</ans:numeroConselhoProfissional>
<ans:UF>35</ans:UF>
<ans:CBOS>225125</ans:CBOS>
</ans:profissionalSolicitante>
</ans:dadosSolicitante>
<ans:dadosSolicitacao>
<ans:dataSolicitacao>2025-09-30</ans:dataSolicitacao>
<ans:caraterAtendimento>2</ans:caraterAtendimento>
<ans:indicacaoClinica>CEFALEIA</ans:indicacaoClinica>
</ans:dadosSolicitacao>
<ans:dadosExecutante>
<ans:contratadoExecutante>
<ans:codigoPrestadorNaOperadora>110020</ans:codigoPrestadorNaOperadora>
</ans:contratadoExecutante>
<ans:CNES>2097117</ans:CNES>
</ans:dadosExecutante>
<ans:dadosAtendimento>
<ans:tipoAtendimento>04</ans:tipoAtendimento>
<ans:indicacaoAcidente>9</ans:indicacaoAcidente>
<ans:tipoConsulta>1</ans:tipoConsulta>
<ans:regimeAtendimento>04</ans:regimeAtendimento>
</ans:dadosAtendimento>
<ans:procedimentosExecutados>
<ans:procedimentoExecutado>
<ans:sequencialItem>1</ans:sequencialItem>
<ans:dataExecucao>2025-09-30</ans:dataExecucao>
<ans:horaInicial>15:22:18</ans:horaInicial>
<ans:horaFinal>15:22:18</ans:horaFinal>
<ans:procedimento>
<ans:codigoTabela>98</ans:codigoTabela>
<ans:codigoProcedimento>98200709</ans:codigoProcedimento>
<ans:descricaoProcedimento>Consulta De Urgencia Global</ans:descricaoProcedimento>
</ans:procedimento>
<ans:quantidadeExecutada>1</ans:quantidadeExecutada>
<ans:viaAcesso>1</ans:viaAcesso>
<ans:tecnicaUtilizada>1</ans:tecnicaUtilizada>
<ans:reducaoAcrescimo>1.00</ans:reducaoAcrescimo>
<ans:valorUnitario>99.08</ans:valorUnitario>
<ans:valorTotal>99.08</ans:valorTotal>
<ans:equipeSadt>
<ans:grauPart>12</ans:grauPart>
<ans:codProfissional>
<ans:codigoPrestadorNaOperadora>110020</ans:codigoPrestadorNaOperadora>
</ans:codProfissional>
<ans:nomeProf>Ronaldo Gonçalves Da Silva</ans:nomeProf>
<ans:conselho>06</ans:conselho>
<ans:numeroConselhoProfissional>139120</ans:numeroConselhoProfissional>
<ans:UF>35</ans:UF>
<ans:CBOS>225125</ans:CBOS>
</ans:equipeSadt>
</ans:procedimentoExecutado>
<ans:procedimentoExecutado>
<ans:sequencialItem>2</ans:sequencialItem>
<ans:dataExecucao>2025-09-30</ans:dataExecucao>
<ans:horaInicial>16:18:20</ans:horaInicial>
<ans:horaFinal>16:18:20</ans:horaFinal>
<ans:procedimento>
<ans:codigoTabela>22</ans:codigoTabela>
<ans:codigoProcedimento>10101039</ans:codigoProcedimento>
<ans:descricaoProcedimento>Consulta Em Pronto Socorro</ans:descricaoProcedimento>
</ans:procedimento>
<ans:quantidadeExecutada>1</ans:quantidadeExecutada>
<ans:viaAcesso>1</ans:viaAcesso>
<ans:tecnicaUtilizada>1</ans:tecnicaUtilizada>
<ans:reducaoAcrescimo>1.00</ans:reducaoAcrescimo>
<ans:valorUnitario>85.35</ans:valorUnitario>
<ans:valorTotal>85.35</ans:valorTotal>
<ans:equipeSadt>
<ans:grauPart>12</ans:grauPart>
<ans:codProfissional>
<ans:cpfContratado>00000263739</ans:cpfContratado>
</ans:codProfissional>
<ans:nomeProf>Matheus Alberto Fogolin Elias</ans:nomeProf>
<ans:conselho>06</ans:conselho>
<ans:numeroConselhoProfissional>263739</ans:numeroConselhoProfissional>
<ans:UF>35</ans:UF>
<ans:CBOS>225125</ans:CBOS>
</ans:equipeSadt>
</ans:procedimentoExecutado>
</ans:procedimentosExecutados>
<ans:valorTotal>
<ans:valorProcedimentos>184.43</ans:valorProcedimentos>
<ans:valorTotalGeral>184.43</ans:valorTotalGeral>
</ans:valorTotal>
</ans:guiaSP-SADT>
</ans:guiasTISS>
</ans:loteGuias>
</ans:prestadorParaOperadora>
<ans:epilogo>
<ans:hash>2d12a3b800866e941890e24ea55444b0</ans:hash>
</ans:epilogo>
</ans:mensagemTISS>